{
  "serviceName": "Amazon EMR on EKS (EMR Containers)",
  "servicePrefix": "emr-containers",
  "url": "https://docs.aws.amazon.com/service-authorization/latest/reference/./list_amazonemroneksemrcontainers.html",
  "actions": [
    {
      "name": "CancelJobRun",
      "documentationUrl": "https://docs.aws.amazon.com/emr-on-eks/latest/APIReference/API_CancelJobRun.html",
      "description": "Grants permission to cancel a job run",
      "accessLevel": "Write",
      "resourceTypes": [
        "jobRun*"
      ],
      "conditionKeys": [],
      "dependentActions": []
    },
    {
      "name": "CreateJobTemplate",
      "documentationUrl": "https://docs.aws.amazon.com/emr-on-eks/latest/APIReference/API_CreateJobTemplate.html",
      "description": "Grants permission to create a job template",
      "accessLevel": "Write",
      "resourceTypes": [],
      "conditionKeys": [
        "aws:RequestTag/${TagKey}",
        "aws:TagKeys"
      ],
      "dependentActions": []
    },
    {
      "name": "CreateManagedEndpoint",
      "documentationUrl": "https://docs.aws.amazon.com/emr-on-eks/latest/APIReference/API_CreateManagedEndpoint.html",
      "description": "Grants permission to create a managed endpoint",
      "accessLevel": "Write",
      "resourceTypes": [
        "virtualCluster*"
      ],
      "conditionKeys": [
        "aws:RequestTag/${TagKey}",
        "aws:TagKeys",
        "emr-containers:ExecutionRoleArn"
      ],
      "dependentActions": []
    },
    {
      "name": "CreateVirtualCluster",
      "documentationUrl": "https://docs.aws.amazon.com/emr-on-eks/latest/APIReference/API_CreateVirtualCluster.html",
      "description": "Grants permission to create a virtual cluster",
      "accessLevel": "Write",
      "resourceTypes": [],
      "conditionKeys": [
        "aws:RequestTag/${TagKey}",
        "aws:TagKeys"
      ],
      "dependentActions": []
    },
    {
      "name": "DeleteJobTemplate",
      "documentationUrl": "https://docs.aws.amazon.com/emr-on-eks/latest/APIReference/API_DeleteJobTemplate.html",
      "description": "Grants permission to delete a job template",
      "accessLevel": "Write",
      "resourceTypes": [
        "jobTemplate*"
      ],
      "conditionKeys": [],
      "dependentActions": []
    },
    {
      "name": "DeleteManagedEndpoint",
      "documentationUrl": "https://docs.aws.amazon.com/emr-on-eks/latest/APIReference/API_DeleteManagedEndpoint.html",
      "description": "Grants permission to delete a managed endpoint",
      "accessLevel": "Write",
      "resourceTypes": [
        "managedEndpoint*"
      ],
      "conditionKeys": [],
      "dependentActions": []
    },
    {
      "name": "DeleteVirtualCluster",
      "documentationUrl": "https://docs.aws.amazon.com/emr-on-eks/latest/APIReference/API_DeleteVirtualCluster.html",
      "description": "Grants permission to delete a virtual cluster",
      "accessLevel": "Write",
      "resourceTypes": [
        "virtualCluster*"
      ],
      "conditionKeys": [],
      "dependentActions": []
    },
    {
      "name": "DescribeJobRun",
      "documentationUrl": "https://docs.aws.amazon.com/emr-on-eks/latest/APIReference/API_DescribeJobRun.html",
      "description": "Grants permission to describe a job run",
      "accessLevel": "Read",
      "resourceTypes": [
        "jobRun*"
      ],
      "conditionKeys": [],
      "dependentActions": []
    },
    {
      "name": "DescribeJobTemplate",
      "documentationUrl": "https://docs.aws.amazon.com/emr-on-eks/latest/APIReference/API_DescribeJobTemplate.html",
      "description": "Grants permission to describe a job template",
      "accessLevel": "Read",
      "resourceTypes": [
        "jobTemplate*"
      ],
      "conditionKeys": [],
      "dependentActions": []
    },
    {
      "name": "DescribeManagedEndpoint",
      "documentationUrl": "https://docs.aws.amazon.com/emr-on-eks/latest/APIReference/API_DescribeManagedEndpoint.html",
      "description": "Grants permission to describe a managed endpoint",
      "accessLevel": "Read",
      "resourceTypes": [
        "managedEndpoint*"
      ],
      "conditionKeys": [],
      "dependentActions": []
    },
    {
      "name": "DescribeVirtualCluster",
      "documentationUrl": "https://docs.aws.amazon.com/emr-on-eks/latest/APIReference/API_DescribeVirtualCluster.html",
      "description": "Grants permission to describe a virtual cluster",
      "accessLevel": "Read",
      "resourceTypes": [
        "virtualCluster*"
      ],
      "conditionKeys": [],
      "dependentActions": []
    },
    {
      "name": "GetManagedEndpointSessionCredentials",
      "documentationUrl": "https://docs.aws.amazon.com/emr-on-eks/latest/APIReference/API_GetManagedEndpointSessionCredentials.html",
      "description": "Grants permission to generate a session token used to connect to a managed endpoint",
      "accessLevel": "Write",
      "resourceTypes": [
        "managedEndpoint*"
      ],
      "conditionKeys": [],
      "dependentActions": []
    },
    {
      "name": "ListJobRuns",
      "documentationUrl": "https://docs.aws.amazon.com/emr-on-eks/latest/APIReference/API_ListJobRuns.html",
      "description": "Grants permission to list job runs associated with a virtual cluster",
      "accessLevel": "List",
      "resourceTypes": [
        "virtualCluster*"
      ],
      "conditionKeys": [],
      "dependentActions": []
    },
    {
      "name": "ListJobTemplates",
      "documentationUrl": "https://docs.aws.amazon.com/emr-on-eks/latest/APIReference/API_ListJobTemplates.html",
      "description": "Grants permission to list job templates",
      "accessLevel": "List",
      "resourceTypes": [],
      "conditionKeys": [],
      "dependentActions": []
    },
    {
      "name": "ListManagedEndpoints",
      "documentationUrl": "https://docs.aws.amazon.com/emr-on-eks/latest/APIReference/API_ListManagedEndpoints.html",
      "description": "Grants permission to list managed endpoints associated with a virtual cluster",
      "accessLevel": "List",
      "resourceTypes": [
        "virtualCluster*"
      ],
      "conditionKeys": [],
      "dependentActions": []
    },
    {
      "name": "ListTagsForResource",
      "documentationUrl": "https://docs.aws.amazon.com/emr-on-eks/latest/APIReference/API_ListTagsForResource.html",
      "description": "Grants permission to list tags for the specified resource",
      "accessLevel": "List",
      "resourceTypes": [
        "jobRun",
        "jobTemplate",
        "managedEndpoint",
        "virtualCluster"
      ],
      "conditionKeys": [],
      "dependentActions": []
    },
    {
      "name": "ListVirtualClusters",
      "documentationUrl": "https://docs.aws.amazon.com/emr-on-eks/latest/APIReference/API_ListVirtualClusters.html",
      "description": "Grants permission to list virtual clusters",
      "accessLevel": "List",
      "resourceTypes": [],
      "conditionKeys": [],
      "dependentActions": []
    },
    {
      "name": "StartJobRun",
      "documentationUrl": "https://docs.aws.amazon.com/emr-on-eks/latest/APIReference/API_StartJobRun.html",
      "description": "Grants permission to start a job run",
      "accessLevel": "Write",
      "resourceTypes": [
        "virtualCluster*"
      ],
      "conditionKeys": [
        "aws:RequestTag/${TagKey}",
        "aws:TagKeys",
        "emr-containers:ExecutionRoleArn",
        "emr-containers:JobTemplateArn"
      ],
      "dependentActions": []
    },
    {
      "name": "TagResource",
      "documentationUrl": "https://docs.aws.amazon.com/emr-on-eks/latest/APIReference/API_TagResource.html",
      "description": "Grants permission to tag the specified resource",
      "accessLevel": "Tagging",
      "resourceTypes": [
        "jobRun",
        "jobTemplate",
        "managedEndpoint",
        "virtualCluster"
      ],
      "conditionKeys": [
        "aws:RequestTag/${TagKey}",
        "aws:TagKeys"
      ],
      "dependentActions": []
    },
    {
      "name": "UntagResource",
      "documentationUrl": "https://docs.aws.amazon.com/emr-on-eks/latest/APIReference/API_UntagResource.html",
      "description": "Grants permission to untag the specified resource",
      "accessLevel": "Tagging",
      "resourceTypes": [
        "jobRun",
        "jobTemplate",
        "managedEndpoint",
        "virtualCluster"
      ],
      "conditionKeys": [
        "aws:TagKeys"
      ],
      "dependentActions": []
    }
  ]
}