{
  "serviceName": "Amazon Bedrock",
  "servicePrefix": "bedrock",
  "url": "https://docs.aws.amazon.com/service-authorization/latest/reference/./list_amazonbedrock.html",
  "actions": [
    {
      "name": "AllowVendedLogDeliveryForResource",
      "documentationUrl": "https://docs.aws.amazon.com/bedrock/latest/APIReference/welcome.html",
      "description": "Grants permission to configure vended log delivery for a knowledge base",
      "accessLevel": "Permissions management",
      "resourceTypes": [
        "knowledge-base"
      ],
      "conditionKeys": [],
      "dependentActions": []
    },
    {
      "name": "ApplyGuardrail",
      "documentationUrl": "https://docs.aws.amazon.com/bedrock/latest/APIReference/welcome.html",
      "description": "Grants permission to apply a guardrail",
      "accessLevel": "Read",
      "resourceTypes": [
        "guardrail*"
      ],
      "conditionKeys": [],
      "dependentActions": []
    },
    {
      "name": "AssociateAgentCollaborator",
      "documentationUrl": "https://docs.aws.amazon.com/bedrock/latest/APIReference/API_agent_AssociateAgentCollaborator.html",
      "description": "Grants permission to associate another existing agent as a collaborator to an existing agent",
      "accessLevel": "Write",
      "resourceTypes": [
        "agent*"
      ],
      "conditionKeys": [],
      "dependentActions": []
    },
    {
      "name": "AssociateAgentKnowledgeBase",
      "documentationUrl": "https://docs.aws.amazon.com/bedrock/latest/APIReference/API_agent_AssociateAgentKnowledgeBase.html",
      "description": "Grants permission to associate a knowledge base with an agent",
      "accessLevel": "Write",
      "resourceTypes": [
        "agent*",
        "knowledge-base*"
      ],
      "conditionKeys": [],
      "dependentActions": []
    },
    {
      "name": "AssociateThirdPartyKnowledgeBase",
      "documentationUrl": "https://docs.aws.amazon.com/bedrock/latest/APIReference/welcome.html",
      "description": "Grants permission to use 3rd party platform to store knowledge data",
      "accessLevel": "Write",
      "resourceTypes": [],
      "conditionKeys": [
        "bedrock:ThirdPartyKnowledgeBaseCredentialsSecretArn"
      ],
      "dependentActions": []
    },
    {
      "name": "BatchDeleteEvaluationJob",
      "documentationUrl": "https://docs.aws.amazon.com/bedrock/latest/APIReference/API_BatchDeleteEvaluationJob.html",
      "description": "Grants permission to batch delete list of bedrock evaluation jobs",
      "accessLevel": "Write",
      "resourceTypes": [
        "evaluation-job*"
      ],
      "conditionKeys": [],
      "dependentActions": []
    },
    {
      "name": "CreateAgent",
      "documentationUrl": "https://docs.aws.amazon.com/bedrock/latest/APIReference/API_agent_CreateAgent.html",
      "description": "Grants permission to create a new agent and a test agent alias pointing to the DRAFT agent version",
      "accessLevel": "Write",
      "resourceTypes": [],
      "conditionKeys": [
        "aws:RequestTag/${TagKey}",
        "aws:TagKeys"
      ],
      "dependentActions": []
    },
    {
      "name": "CreateAgentActionGroup",
      "documentationUrl": "https://docs.aws.amazon.com/bedrock/latest/APIReference/API_agent_CreateAgentActionGroup.html",
      "description": "Grants permission to create a new action group in an existing agent",
      "accessLevel": "Write",
      "resourceTypes": [
        "agent*"
      ],
      "conditionKeys": [
        "aws:RequestTag/${TagKey}",
        "aws:TagKeys"
      ],
      "dependentActions": []
    },
    {
      "name": "CreateAgentAlias",
      "documentationUrl": "https://docs.aws.amazon.com/bedrock/latest/APIReference/API_agent_CreateAgentAlias.html",
      "description": "Grants permission to create a new alias for an agent",
      "accessLevel": "Write",
      "resourceTypes": [
        "agent*"
      ],
      "conditionKeys": [
        "aws:RequestTag/${TagKey}",
        "aws:TagKeys"
      ],
      "dependentActions": []
    },
    {
      "name": "CreateBlueprint",
      "documentationUrl": "https://docs.aws.amazon.com/bedrock/latest/APIReference/API_data-automation_CreateBlueprint.html",
      "description": "Grants permission to create a blueprint for custom output from data automation",
      "accessLevel": "Write",
      "resourceTypes": [],
      "conditionKeys": [],
      "dependentActions": []
    },
    {
      "name": "CreateBlueprintVersion",
      "documentationUrl": "https://docs.aws.amazon.com/bedrock/latest/APIReference/API_data-automation_CreateBlueprintVersion.html",
      "description": "Grants permission to create a new version for an existing blueprint",
      "accessLevel": "Write",
      "resourceTypes": [
        "blueprint*"
      ],
      "conditionKeys": [],
      "dependentActions": []
    },
    {
      "name": "CreateDataAutomationProject",
      "documentationUrl": "https://docs.aws.amazon.com/bedrock/latest/APIReference/API_data-automation_CreateDataAutomationProject.html",
      "description": "Grants permission to create a data automation project",
      "accessLevel": "Write",
      "resourceTypes": [
        "blueprint"
      ],
      "conditionKeys": [],
      "dependentActions": []
    },
    {
      "name": "CreateDataSource",
      "documentationUrl": "https://docs.aws.amazon.com/bedrock/latest/APIReference/API_agent_CreateDataSource.html",
      "description": "Grants permission to create a data source",
      "accessLevel": "Write",
      "resourceTypes": [
        "knowledge-base*"
      ],
      "conditionKeys": [],
      "dependentActions": []
    },
    {
      "name": "CreateEvaluationJob",
      "documentationUrl": "https://docs.aws.amazon.com/bedrock/latest/APIReference/API_CreateEvaluationJob.html",
      "description": "Grants permission to create a job for evaluation foundation models or custom models",
      "accessLevel": "Write",
      "resourceTypes": [
        "custom-model*",
        "default-prompt-router*",
        "foundation-model*",
        "prompt-router*"
      ],
      "conditionKeys": [
        "aws:RequestTag/${TagKey}",
        "aws:TagKeys"
      ],
      "dependentActions": []
    },
    {
      "name": "CreateFlow",
      "documentationUrl": "https://docs.aws.amazon.com/bedrock/latest/APIReference/API_agent_CreateFlow.html",
      "description": "Grants permission to create a prompt flow",
      "accessLevel": "Write",
      "resourceTypes": [],
      "conditionKeys": [
        "aws:RequestTag/${TagKey}",
        "aws:TagKeys"
      ],
      "dependentActions": []
    },
    {
      "name": "CreateFlowAlias",
      "documentationUrl": "https://docs.aws.amazon.com/bedrock/latest/APIReference/API_agent_CreateFlowAlias.html",
      "description": "Grants permission to create an alias of a prompt flow",
      "accessLevel": "Write",
      "resourceTypes": [
        "flow*"
      ],
      "conditionKeys": [
        "aws:RequestTag/${TagKey}",
        "aws:TagKeys"
      ],
      "dependentActions": []
    },
    {
      "name": "CreateFlowVersion",
      "documentationUrl": "https://docs.aws.amazon.com/bedrock/latest/APIReference/API_agent_CreateFlowVersion.html",
      "description": "Grants permission to create an immutable version of a prompt flow",
      "accessLevel": "Write",
      "resourceTypes": [
        "flow*"
      ],
      "conditionKeys": [],
      "dependentActions": []
    },
    {
      "name": "CreateFoundationModelAgreement",
      "documentationUrl": "https://docs.aws.amazon.com/service-authorization/latest/reference/list_amazonbedrock.html",
      "description": "Grants permission to create a new foundation model agreement",
      "accessLevel": "Write",
      "resourceTypes": [],
      "conditionKeys": [],
      "dependentActions": []
    },
    {
      "name": "CreateGuardrail",
      "documentationUrl": "https://docs.aws.amazon.com/bedrock/latest/APIReference/welcome.html",
      "description": "Grants permission to create a new guardrail",
      "accessLevel": "Write",
      "resourceTypes": [],
      "conditionKeys": [
        "aws:RequestTag/${TagKey}",
        "aws:TagKeys"
      ],
      "dependentActions": []
    },
    {
      "name": "CreateGuardrailVersion",
      "documentationUrl": "https://docs.aws.amazon.com/bedrock/latest/APIReference/welcome.html",
      "description": "Grants permission to create a new guardrail version",
      "accessLevel": "Write",
      "resourceTypes": [
        "guardrail*"
      ],
      "conditionKeys": [],
      "dependentActions": []
    },
    {
      "name": "CreateInferenceProfile",
      "documentationUrl": "https://docs.aws.amazon.com/bedrock/latest/APIReference/API_CreateInferenceProfile.html",
      "description": "Grants permission to create inference profiles",
      "accessLevel": "Write",
      "resourceTypes": [
        "application-inference-profile*",
        "foundation-model*",
        "inference-profile*"
      ],
      "conditionKeys": [
        "aws:RequestTag/${TagKey}",
        "aws:TagKeys"
      ],
      "dependentActions": []
    },
    {
      "name": "CreateInvocation",
      "documentationUrl": "https://docs.aws.amazon.com/bedrock/latest/APIReference/API_agent-runtime_CreateInvocation.html",
      "description": "Grants permission to create a new invocation in an existing session",
      "accessLevel": "Write",
      "resourceTypes": [
        "session*"
      ],
      "conditionKeys": [],
      "dependentActions": []
    },
    {
      "name": "CreateKnowledgeBase",
      "documentationUrl": "https://docs.aws.amazon.com/bedrock/latest/APIReference/API_agent_CreateKnowledgeBase.html",
      "description": "Grants permission to create a knowledge base",
      "accessLevel": "Write",
      "resourceTypes": [],
      "conditionKeys": [
        "aws:RequestTag/${TagKey}",
        "aws:TagKeys"
      ],
      "dependentActions": []
    },
    {
      "name": "CreateMarketplaceModelEndpoint",
      "documentationUrl": "API_CreateMarketplaceModelEndpoint",
      "description": "Grants permission to create a marketplace model endpoint",
      "accessLevel": "Write",
      "resourceTypes": [],
      "conditionKeys": [],
      "dependentActions": []
    },
    {
      "name": "CreateModelCopyJob",
      "documentationUrl": "https://docs.aws.amazon.com/bedrock/latest/APIReference/API_CreateModelCopyJob.html",
      "description": "Grants permission to create a job for copying a custom model across region or across account",
      "accessLevel": "Write",
      "resourceTypes": [
        "custom-model*"
      ],
      "conditionKeys": [
        "aws:RequestTag/${TagKey}",
        "aws:TagKeys"
      ],
      "dependentActions": []
    },
    {
      "name": "CreateModelCustomizationJob",
      "documentationUrl": "https://docs.aws.amazon.com/bedrock/latest/APIReference/API_CreateModelCustomizationJob.html",
      "description": "Grants permission to create a job for customizing the model with your custom training data",
      "accessLevel": "Write",
      "resourceTypes": [
        "custom-model*",
        "foundation-model*"
      ],
      "conditionKeys": [
        "aws:RequestTag/${TagKey}",
        "aws:TagKeys"
      ],
      "dependentActions": []
    },
    {
      "name": "CreateModelEvaluationJob",
      "documentationUrl": "https://docs.aws.amazon.com/bedrock/latest/APIReference/API_CreateModelEvaluationJob.html",
      "description": "Grants permission to create a job for evaluation foundation models or custom models",
      "accessLevel": "Write",
      "resourceTypes": [
        "custom-model*",
        "foundation-model*"
      ],
      "conditionKeys": [
        "aws:RequestTag/${TagKey}",
        "aws:TagKeys"
      ],
      "dependentActions": []
    },
    {
      "name": "CreateModelImportJob",
      "documentationUrl": "https://docs.aws.amazon.com/bedrock/latest/APIReference/API_CreateModelImportJob.html",
      "description": "Grants permission to create a job for importing model into Bedrock",
      "accessLevel": "Write",
      "resourceTypes": [],
      "conditionKeys": [
        "aws:RequestTag/${TagKey}",
        "aws:TagKeys"
      ],
      "dependentActions": []
    },
    {
      "name": "CreateModelInvocationJob",
      "documentationUrl": "https://docs.aws.amazon.com/bedrock/latest/APIReference/API_CreateModelInvocationJob.html",
      "description": "Grants permission to create a new model invocation job",
      "accessLevel": "Write",
      "resourceTypes": [
        "custom-model*",
        "foundation-model*",
        "model-invocation-job*"
      ],
      "conditionKeys": [
        "aws:RequestTag/${TagKey}",
        "aws:TagKeys"
      ],
      "dependentActions": []
    },
    {
      "name": "CreatePrompt",
      "documentationUrl": "https://docs.aws.amazon.com/bedrock/latest/APIReference/API_agent_CreatePrompt.html",
      "description": "Grants permission to create a prompt",
      "accessLevel": "Write",
      "resourceTypes": [],
      "conditionKeys": [
        "aws:RequestTag/${TagKey}",
        "aws:TagKeys"
      ],
      "dependentActions": []
    },
    {
      "name": "CreatePromptRouter",
      "documentationUrl": "https://docs.aws.amazon.com/bedrock/latest/APIReference/API_CreatePromptRouter.html",
      "description": "Grants permission to create a custom prompt router",
      "accessLevel": "Write",
      "resourceTypes": [
        "application-inference-profile*",
        "foundation-model*",
        "inference-profile*"
      ],
      "conditionKeys": [
        "aws:RequestTag/${TagKey}",
        "aws:TagKeys"
      ],
      "dependentActions": []
    },
    {
      "name": "CreatePromptVersion",
      "documentationUrl": "https://docs.aws.amazon.com/bedrock/latest/APIReference/API_agent_CreatePromptVersion.html",
      "description": "Grants permission to create a version of a prompt",
      "accessLevel": "Write",
      "resourceTypes": [
        "prompt*"
      ],
      "conditionKeys": [
        "aws:RequestTag/${TagKey}",
        "aws:TagKeys"
      ],
      "dependentActions": []
    },
    {
      "name": "CreateProvisionedModelThroughput",
      "documentationUrl": "https://docs.aws.amazon.com/bedrock/latest/APIReference/API_CreateProvisionedModelThroughput.html",
      "description": "Grants permission to create a new provisioned model throughput",
      "accessLevel": "Write",
      "resourceTypes": [
        "custom-model*",
        "foundation-model*"
      ],
      "conditionKeys": [
        "aws:RequestTag/${TagKey}",
        "aws:TagKeys"
      ],
      "dependentActions": []
    },
    {
      "name": "CreateSession",
      "documentationUrl": "https://docs.aws.amazon.com/bedrock/latest/APIReference/API_agent-runtime_CreateSession.html",
      "description": "Grants permission to create a new session",
      "accessLevel": "Write",
      "resourceTypes": [],
      "conditionKeys": [
        "aws:RequestTag/${TagKey}",
        "aws:TagKeys"
      ],
      "dependentActions": []
    },
    {
      "name": "DeleteAgent",
      "documentationUrl": "https://docs.aws.amazon.com/bedrock/latest/APIReference/API_agent_DeleteAgent.html",
      "description": "Grants permission to delete an Agent that you created earlier",
      "accessLevel": "Write",
      "resourceTypes": [
        "agent*"
      ],
      "conditionKeys": [],
      "dependentActions": []
    },
    {
      "name": "DeleteAgentActionGroup",
      "documentationUrl": "https://docs.aws.amazon.com/bedrock/latest/APIReference/API_agent_DeleteAgentActionGroup.html",
      "description": "Grants permission to delete an actionGroup that you created earlier",
      "accessLevel": "Write",
      "resourceTypes": [
        "agent*"
      ],
      "conditionKeys": [],
      "dependentActions": []
    },
    {
      "name": "DeleteAgentAlias",
      "documentationUrl": "https://docs.aws.amazon.com/bedrock/latest/APIReference/API_agent_DeleteAgentAlias.html",
      "description": "Grants permission to delete an AgentAlias that you created earlier",
      "accessLevel": "Write",
      "resourceTypes": [
        "agent-alias*"
      ],
      "conditionKeys": [],
      "dependentActions": []
    },
    {
      "name": "DeleteAgentMemory",
      "documentationUrl": "https://docs.aws.amazon.com/bedrock/latest/APIReference/API_agent-runtime_DeleteAgentMemory.html",
      "description": "Grants permission to delete existing memory for an alias",
      "accessLevel": "Write",
      "resourceTypes": [
        "agent-alias*"
      ],
      "conditionKeys": [],
      "dependentActions": []
    },
    {
      "name": "DeleteAgentVersion",
      "documentationUrl": "https://docs.aws.amazon.com/bedrock/latest/APIReference/API_agent_DeleteAgentVersion.html",
      "description": "Grants permission to delete an Agent Version that you created earlier",
      "accessLevel": "Write",
      "resourceTypes": [
        "agent*"
      ],
      "conditionKeys": [],
      "dependentActions": []
    },
    {
      "name": "DeleteBlueprint",
      "documentationUrl": "https://docs.aws.amazon.com/bedrock/latest/APIReference/API_data-automation_DeleteBlueprint.html",
      "description": "Grants permission to delete a blueprint for data automation",
      "accessLevel": "Write",
      "resourceTypes": [
        "blueprint*"
      ],
      "conditionKeys": [],
      "dependentActions": []
    },
    {
      "name": "DeleteCustomModel",
      "documentationUrl": "https://docs.aws.amazon.com/bedrock/latest/APIReference/API_DeleteCustomModel.html",
      "description": "Grants permission to delete a custom model that you created earlier",
      "accessLevel": "Write",
      "resourceTypes": [
        "custom-model*"
      ],
      "conditionKeys": [],
      "dependentActions": []
    },
    {
      "name": "DeleteDataAutomationProject",
      "documentationUrl": "https://docs.aws.amazon.com/bedrock/latest/APIReference/API_data-automation_DeleteDataAutomationProject.html",
      "description": "Grants permission to delete a data automation project",
      "accessLevel": "Write",
      "resourceTypes": [
        "data-automation-project*"
      ],
      "conditionKeys": [],
      "dependentActions": []
    },
    {
      "name": "DeleteDataSource",
      "documentationUrl": "https://docs.aws.amazon.com/bedrock/latest/APIReference/API_agent_DeleteDataSource.html",
      "description": "Grants permission to delete a data source",
      "accessLevel": "Write",
      "resourceTypes": [
        "knowledge-base*"
      ],
      "conditionKeys": [],
      "dependentActions": []
    },
    {
      "name": "DeleteFlow",
      "documentationUrl": "https://docs.aws.amazon.com/bedrock/latest/APIReference/API_agent_DeleteFlow.html",
      "description": "Grants permission to delete a prompt flow",
      "accessLevel": "Write",
      "resourceTypes": [
        "flow*"
      ],
      "conditionKeys": [],
      "dependentActions": []
    },
    {
      "name": "DeleteFlowAlias",
      "documentationUrl": "https://docs.aws.amazon.com/bedrock/latest/APIReference/API_agent_DeleteFlowAlias.html",
      "description": "Grants permission to delete an alias of a prompt flow",
      "accessLevel": "Write",
      "resourceTypes": [
        "flow-alias*"
      ],
      "conditionKeys": [],
      "dependentActions": []
    },
    {
      "name": "DeleteFlowVersion",
      "documentationUrl": "https://docs.aws.amazon.com/bedrock/latest/APIReference/API_agent_DeleteFlowVersion.html",
      "description": "Grants permission to delete a version of a prompt flow",
      "accessLevel": "Write",
      "resourceTypes": [
        "flow*"
      ],
      "conditionKeys": [],
      "dependentActions": []
    },
    {
      "name": "DeleteFoundationModelAgreement",
      "documentationUrl": "https://docs.aws.amazon.com/service-authorization/latest/reference/list_amazonbedrock.html",
      "description": "Grants permission to delete a foundation model agreement that you created earlier",
      "accessLevel": "Write",
      "resourceTypes": [],
      "conditionKeys": [],
      "dependentActions": []
    },
    {
      "name": "DeleteGuardrail",
      "documentationUrl": "https://docs.aws.amazon.com/bedrock/latest/APIReference/welcome.html",
      "description": "Grants permission to delete a guardrail or its version",
      "accessLevel": "Write",
      "resourceTypes": [
        "guardrail*"
      ],
      "conditionKeys": [],
      "dependentActions": []
    },
    {
      "name": "DeleteImportedModel",
      "documentationUrl": "https://docs.aws.amazon.com/bedrock/latest/APIReference/API_DeleteImportedModel.html",
      "description": "Grants permission to delete previously created Bedrock imported model",
      "accessLevel": "Write",
      "resourceTypes": [
        "imported-model*"
      ],
      "conditionKeys": [],
      "dependentActions": []
    },
    {
      "name": "DeleteInferenceProfile",
      "documentationUrl": "https://docs.aws.amazon.com/bedrock/latest/APIReference/API_DeleteInferenceProfile.html",
      "description": "Grants permission to delete inference profiles",
      "accessLevel": "Write",
      "resourceTypes": [
        "application-inference-profile*"
      ],
      "conditionKeys": [],
      "dependentActions": []
    },
    {
      "name": "DeleteKnowledgeBase",
      "documentationUrl": "https://docs.aws.amazon.com/bedrock/latest/APIReference/API_agent_DeleteKnowledgeBase.html",
      "description": "Grants permission to delete a knowledge base",
      "accessLevel": "Write",
      "resourceTypes": [
        "knowledge-base*"
      ],
      "conditionKeys": [],
      "dependentActions": []
    },
    {
      "name": "DeleteKnowledgeBaseDocuments",
      "documentationUrl": "https://docs.aws.amazon.com/bedrock/latest/APIReference/API_agent_DeleteKnowledgeBaseDocuments.html",
      "description": "Grants permission to delete documents from a knowledge base",
      "accessLevel": "Write",
      "resourceTypes": [
        "knowledge-base*"
      ],
      "conditionKeys": [],
      "dependentActions": []
    },
    {
      "name": "DeleteMarketplaceModelAgreement",
      "documentationUrl": "https://docs.aws.amazon.com/service-authorization/latest/reference/list_amazonbedrock.html",
      "description": "Grants permission to unsubscribe from a bedrock marketplace enabled AWS marketplace model",
      "accessLevel": "Write",
      "resourceTypes": [],
      "conditionKeys": [],
      "dependentActions": []
    },
    {
      "name": "DeleteMarketplaceModelEndpoint",
      "documentationUrl": "API_DeleteMarketplaceModelEndpoint",
      "description": "Grants permission to delete a marketplace model endpoint",
      "accessLevel": "Write",
      "resourceTypes": [
        "bedrock-marketplace-model-endpoint*"
      ],
      "conditionKeys": [],
      "dependentActions": []
    },
    {
      "name": "DeleteModelInvocationLoggingConfiguration",
      "documentationUrl": "https://docs.aws.amazon.com/bedrock/latest/APIReference/API_DeleteModelInvocationLoggingConfiguration.html",
      "description": "Grants permission to delete an existing Invocation logging configuration",
      "accessLevel": "Write",
      "resourceTypes": [],
      "conditionKeys": [],
      "dependentActions": []
    },
    {
      "name": "DeletePrompt",
      "documentationUrl": "https://docs.aws.amazon.com/bedrock/latest/APIReference/API_agent_DeletePrompt.html",
      "description": "Grants permission to delete a prompt or its version",
      "accessLevel": "Write",
      "resourceTypes": [
        "prompt*",
        "prompt-version*"
      ],
      "conditionKeys": [],
      "dependentActions": []
    },
    {
      "name": "DeletePromptRouter",
      "documentationUrl": "https://docs.aws.amazon.com/bedrock/latest/APIReference/API_DeletePromptRouter.html",
      "description": "Grants permission to delete a custom prompt router",
      "accessLevel": "Write",
      "resourceTypes": [
        "prompt-router*"
      ],
      "conditionKeys": [],
      "dependentActions": []
    },
    {
      "name": "DeleteProvisionedModelThroughput",
      "documentationUrl": "https://docs.aws.amazon.com/bedrock/latest/APIReference/API_DeleteProvisionedModelThroughput.html",
      "description": "Grants permission to delete a provisioned model throughput that you created earlier",
      "accessLevel": "Write",
      "resourceTypes": [
        "provisioned-model*"
      ],
      "conditionKeys": [],
      "dependentActions": []
    },
    {
      "name": "DeleteResourcePolicy",
      "documentationUrl": "https://docs.aws.amazon.com/bedrock/latest/APIReference/API_DeleteResourcePolicy.html",
      "description": "Deletes a previously created Bedrock resource policy",
      "accessLevel": "Write",
      "resourceTypes": [
        "custom-model*"
      ],
      "conditionKeys": [],
      "dependentActions": []
    },
    {
      "name": "DeleteSession",
      "documentationUrl": "https://docs.aws.amazon.com/bedrock/latest/APIReference/API_agent-runtime_DeleteSession.html",
      "description": "Grants permission to delete a Session that you created earlier",
      "accessLevel": "Write",
      "resourceTypes": [
        "session*"
      ],
      "conditionKeys": [],
      "dependentActions": []
    },
    {
      "name": "DeregisterMarketplaceModelEndpoint",
      "documentationUrl": "API_DeregisterMarketplaceModelEndpoint",
      "description": "Grants permission to deregister a marketplace model endpoint to make it unusable in Bedrock Marketplace",
      "accessLevel": "Write",
      "resourceTypes": [
        "bedrock-marketplace-model-endpoint*"
      ],
      "conditionKeys": [],
      "dependentActions": []
    },
    {
      "name": "DetectGeneratedContent",
      "documentationUrl": "https://docs.aws.amazon.com/bedrock/latest/APIReference/welcome.html",
      "description": "Grants permission to detect if the provided content is generated using Amazon Bedrock",
      "accessLevel": "Read",
      "resourceTypes": [
        "foundation-model*"
      ],
      "conditionKeys": [],
      "dependentActions": []
    },
    {
      "name": "DisassociateAgentCollaborator",
      "documentationUrl": "https://docs.aws.amazon.com/bedrock/latest/APIReference/API_agent_DisassociateAgentCollaborator.html",
      "description": "Grants permission to diassociate a collaborator that you associated earlier",
      "accessLevel": "Write",
      "resourceTypes": [
        "agent*"
      ],
      "conditionKeys": [],
      "dependentActions": []
    },
    {
      "name": "DisassociateAgentKnowledgeBase",
      "documentationUrl": "https://docs.aws.amazon.com/bedrock/latest/APIReference/API_agent_DisassociateAgentKnowledgeBase.html",
      "description": "Grants permission to disassociate a knowledge base from the agent",
      "accessLevel": "Write",
      "resourceTypes": [
        "agent*",
        "knowledge-base*"
      ],
      "conditionKeys": [],
      "dependentActions": []
    },
    {
      "name": "EndSession",
      "documentationUrl": "https://docs.aws.amazon.com/bedrock/latest/APIReference/API_agent-runtime_EndSession.html",
      "description": "Grants permission to end a Session that you created earlier",
      "accessLevel": "Write",
      "resourceTypes": [
        "session*"
      ],
      "conditionKeys": [],
      "dependentActions": []
    },
    {
      "name": "GenerateQuery",
      "documentationUrl": "https://docs.aws.amazon.com/bedrock/latest/APIReference/welcome.html",
      "description": "Grants permission to generate queries associated with user input",
      "accessLevel": "Read",
      "resourceTypes": [],
      "conditionKeys": [],
      "dependentActions": []
    },
    {
      "name": "GetAgent",
      "documentationUrl": "https://docs.aws.amazon.com/bedrock/latest/APIReference/API_agent_GetAgent.html",
      "description": "Grants permission to retrieve an existing agent",
      "accessLevel": "Read",
      "resourceTypes": [
        "agent*"
      ],
      "conditionKeys": [],
      "dependentActions": []
    },
    {
      "name": "GetAgentActionGroup",
      "documentationUrl": "https://docs.aws.amazon.com/bedrock/latest/APIReference/API_agent_GetAgentActionGroup.html",
      "description": "Grants permission to retrieve an existing action group",
      "accessLevel": "Read",
      "resourceTypes": [
        "agent*"
      ],
      "conditionKeys": [],
      "dependentActions": []
    },
    {
      "name": "GetAgentAlias",
      "documentationUrl": "https://docs.aws.amazon.com/bedrock/latest/APIReference/API_agent_GetAgentAlias.html",
      "description": "Grants permission to retrieve an existing alias",
      "accessLevel": "Read",
      "resourceTypes": [
        "agent-alias*"
      ],
      "conditionKeys": [],
      "dependentActions": []
    },
    {
      "name": "GetAgentCollaborator",
      "documentationUrl": "https://docs.aws.amazon.com/bedrock/latest/APIReference/API_agent_GetAgentCollaborator.html",
      "description": "Grants permission to retrieve an existing collaborator",
      "accessLevel": "Read",
      "resourceTypes": [
        "agent*"
      ],
      "conditionKeys": [],
      "dependentActions": []
    },
    {
      "name": "GetAgentKnowledgeBase",
      "documentationUrl": "https://docs.aws.amazon.com/bedrock/latest/APIReference/API_agent_GetAgentKnowledgeBase.html",
      "description": "Grants permission to describe a knowledge base associated with an agent",
      "accessLevel": "Read",
      "resourceTypes": [
        "agent*",
        "knowledge-base*"
      ],
      "conditionKeys": [],
      "dependentActions": []
    },
    {
      "name": "GetAgentMemory",
      "documentationUrl": "https://docs.aws.amazon.com/bedrock/latest/APIReference/API_agent-runtime_GetAgentMemory.html",
      "description": "Grants permission to retrieve existing memory for an alias",
      "accessLevel": "Read",
      "resourceTypes": [
        "agent-alias*"
      ],
      "conditionKeys": [],
      "dependentActions": []
    },
    {
      "name": "GetAgentVersion",
      "documentationUrl": "https://docs.aws.amazon.com/bedrock/latest/APIReference/API_agent_GetAgentVersion.html",
      "description": "Grants permission to retrieve an existing version of an agent",
      "accessLevel": "Read",
      "resourceTypes": [
        "agent*"
      ],
      "conditionKeys": [],
      "dependentActions": []
    },
    {
      "name": "GetAsyncInvoke",
      "documentationUrl": "https://docs.aws.amazon.com/bedrock/latest/APIReference/API_GetAsyncInvoke.html",
      "description": "Grants permission to get the properties associated with an asynchronous invocation that you have submitted",
      "accessLevel": "Read",
      "resourceTypes": [
        "async-invoke*"
      ],
      "conditionKeys": [],
      "dependentActions": []
    },
    {
      "name": "GetBlueprint",
      "documentationUrl": "https://docs.aws.amazon.com/bedrock/latest/APIReference/API_data-automation_GetBlueprint.html",
      "description": "Grants permission to retrieve an existing blueprint for data automation",
      "accessLevel": "Read",
      "resourceTypes": [
        "blueprint*"
      ],
      "conditionKeys": [],
      "dependentActions": []
    },
    {
      "name": "GetBlueprintRecommendation",
      "documentationUrl": "https://docs.aws.amazon.com/bedrock/latest/APIReference/welcome.html",
      "description": "Grants permission to retrieve blueprint recommendation",
      "accessLevel": "Read",
      "resourceTypes": [],
      "conditionKeys": [],
      "dependentActions": []
    },
    {
      "name": "GetCustomModel",
      "documentationUrl": "https://docs.aws.amazon.com/bedrock/latest/APIReference/API_GetCustomModel.html",
      "description": "Grants permission to get the properties associated with a Bedrock custom model that you have created",
      "accessLevel": "Read",
      "resourceTypes": [
        "custom-model*"
      ],
      "conditionKeys": [],
      "dependentActions": []
    },
    {
      "name": "GetDataAutomationProject",
      "documentationUrl": "https://docs.aws.amazon.com/bedrock/latest/APIReference/API_data-automation_GetDataAutomationProject.html",
      "description": "Grants permission to retrieve an existing data automation project",
      "accessLevel": "Read",
      "resourceTypes": [
        "data-automation-project*"
      ],
      "conditionKeys": [],
      "dependentActions": []
    },
    {
      "name": "GetDataAutomationStatus",
      "documentationUrl": "https://docs.aws.amazon.com/bedrock/latest/APIReference/API_data-automation-runtime_GetDataAutomationStatus.html",
      "description": "Grants permission to retrieve the status of a data automation invocation job",
      "accessLevel": "Read",
      "resourceTypes": [
        "data-automation-invocation-job*"
      ],
      "conditionKeys": [],
      "dependentActions": []
    },
    {
      "name": "GetDataSource",
      "documentationUrl": "https://docs.aws.amazon.com/bedrock/latest/APIReference/API_agent_GetDataSource.html",
      "description": "Grants permission to retrieve an existing data source",
      "accessLevel": "Read",
      "resourceTypes": [
        "knowledge-base*"
      ],
      "conditionKeys": [],
      "dependentActions": []
    },
    {
      "name": "GetEvaluationJob",
      "documentationUrl": "https://docs.aws.amazon.com/bedrock/latest/APIReference/API_GetEvaluationJob.html",
      "description": "Grants permission to get the properties associated with a evaluation job. Use this operation to get the status of a evaluation job",
      "accessLevel": "Read",
      "resourceTypes": [
        "evaluation-job*"
      ],
      "conditionKeys": [],
      "dependentActions": []
    },
    {
      "name": "GetFlow",
      "documentationUrl": "https://docs.aws.amazon.com/bedrock/latest/APIReference/API_agent_GetFlow.html",
      "description": "Grants permission to retrieve an existing prompt flow",
      "accessLevel": "Read",
      "resourceTypes": [
        "flow*"
      ],
      "conditionKeys": [],
      "dependentActions": []
    },
    {
      "name": "GetFlowAlias",
      "documentationUrl": "https://docs.aws.amazon.com/bedrock/latest/APIReference/API_agent_GetFlowAlias.html",
      "description": "Grants permission to retrieve an existing alias of a prompt flow",
      "accessLevel": "Read",
      "resourceTypes": [
        "flow-alias*"
      ],
      "conditionKeys": [],
      "dependentActions": []
    },
    {
      "name": "GetFlowVersion",
      "documentationUrl": "https://docs.aws.amazon.com/bedrock/latest/APIReference/API_agent_GetFlowVersion.html",
      "description": "Grants permission to retrieve an existing version of a prompt flow",
      "accessLevel": "Read",
      "resourceTypes": [
        "flow*"
      ],
      "conditionKeys": [],
      "dependentActions": []
    },
    {
      "name": "GetFoundationModel",
      "documentationUrl": "https://docs.aws.amazon.com/bedrock/latest/APIReference/API_GetFoundationModel.html",
      "description": "Grants permission to get the properties associated with a Bedrock foundation model",
      "accessLevel": "Read",
      "resourceTypes": [
        "foundation-model*"
      ],
      "conditionKeys": [],
      "dependentActions": []
    },
    {
      "name": "GetFoundationModelAvailability",
      "documentationUrl": "https://docs.aws.amazon.com/service-authorization/latest/reference/list_amazonbedrock.html",
      "description": "Grants permission to get the availability of a foundation model",
      "accessLevel": "Read",
      "resourceTypes": [],
      "conditionKeys": [],
      "dependentActions": []
    },
    {
      "name": "GetGuardrail",
      "documentationUrl": "https://docs.aws.amazon.com/bedrock/latest/APIReference/welcome.html",
      "description": "Grants permission to retrieve a guardrail or its version",
      "accessLevel": "Read",
      "resourceTypes": [
        "guardrail*"
      ],
      "conditionKeys": [],
      "dependentActions": []
    },
    {
      "name": "GetImportedModel",
      "documentationUrl": "https://docs.aws.amazon.com/bedrock/latest/APIReference/API_GetImportedModel.html",
      "description": "Grants permission to get the properties associated with Bedrock imported model",
      "accessLevel": "Read",
      "resourceTypes": [
        "imported-model*"
      ],
      "conditionKeys": [],
      "dependentActions": []
    },
    {
      "name": "GetInferenceProfile",
      "documentationUrl": "https://docs.aws.amazon.com/bedrock/latest/APIReference/API_GetInferenceProfile.html",
      "description": "Grants permission to get the properties associated with an inference profile",
      "accessLevel": "Read",
      "resourceTypes": [
        "application-inference-profile*",
        "inference-profile*"
      ],
      "conditionKeys": [],
      "dependentActions": []
    },
    {
      "name": "GetIngestionJob",
      "documentationUrl": "https://docs.aws.amazon.com/bedrock/latest/APIReference/API_agent_GetIngestionJob.html",
      "description": "Grants permission to retrieve an existing ingestion job",
      "accessLevel": "Read",
      "resourceTypes": [
        "knowledge-base*"
      ],
      "conditionKeys": [],
      "dependentActions": []
    },
    {
      "name": "GetInvocationStep",
      "documentationUrl": "https://docs.aws.amazon.com/bedrock/latest/APIReference/API_agent-runtime_GetInvocationStep.html",
      "description": "Grants permission to get an invocation step from a session",
      "accessLevel": "Read",
      "resourceTypes": [
        "session*"
      ],
      "conditionKeys": [],
      "dependentActions": []
    },
    {
      "name": "GetKnowledgeBase",
      "documentationUrl": "https://docs.aws.amazon.com/bedrock/latest/APIReference/API_agent_GetKnowledgeBase.html",
      "description": "Grants permission to retrieve an existing knowledge base",
      "accessLevel": "Read",
      "resourceTypes": [
        "knowledge-base*"
      ],
      "conditionKeys": [],
      "dependentActions": []
    },
    {
      "name": "GetKnowledgeBaseDocuments",
      "documentationUrl": "https://docs.aws.amazon.com/bedrock/latest/APIReference/API_agent_GetKnowledgeBaseDocuments.html",
      "description": "Grants permission to get details for documents in a knowledge base",
      "accessLevel": "Read",
      "resourceTypes": [
        "knowledge-base*"
      ],
      "conditionKeys": [],
      "dependentActions": []
    },
    {
      "name": "GetMarketplaceModelEndpoint",
      "documentationUrl": "API_GetMarketplaceModelEndpoint",
      "description": "Grants permission to get the properties of a marketplace model endpoint",
      "accessLevel": "Read",
      "resourceTypes": [
        "bedrock-marketplace-model-endpoint*"
      ],
      "conditionKeys": [],
      "dependentActions": []
    },
    {
      "name": "GetModelCopyJob",
      "documentationUrl": "https://docs.aws.amazon.com/bedrock/latest/APIReference/API_GetModelCopyJob.html",
      "description": "Grants permission to get the properties associated with a model-copy job. Use this operation to get the status of a model-copy job",
      "accessLevel": "Read",
      "resourceTypes": [
        "model-copy-job*"
      ],
      "conditionKeys": [],
      "dependentActions": []
    },
    {
      "name": "GetModelCustomizationJob",
      "documentationUrl": "https://docs.aws.amazon.com/bedrock/latest/APIReference/API_GetModelCustomizationJob.html",
      "description": "Grants permission to get the properties associated with a model-customization job. Use this operation to get the status of a model-customization job",
      "accessLevel": "Read",
      "resourceTypes": [
        "model-customization-job*"
      ],
      "conditionKeys": [],
      "dependentActions": []
    },
    {
      "name": "GetModelEvaluationJob",
      "documentationUrl": "https://docs.aws.amazon.com/bedrock/latest/APIReference/API_GetModelEvaluationJob.html",
      "description": "Grants permission to get the properties associated with a model-evaluation job. Use this operation to get the status of a model-evaluation job",
      "accessLevel": "Read",
      "resourceTypes": [
        "model-evaluation-job*"
      ],
      "conditionKeys": [],
      "dependentActions": []
    },
    {
      "name": "GetModelImportJob",
      "documentationUrl": "https://docs.aws.amazon.com/bedrock/latest/APIReference/API_GetModelImportJob.html",
      "description": "Grants permission to get the properties associated with a model import job and is used to get the status of a model import job",
      "accessLevel": "Read",
      "resourceTypes": [
        "model-import-job*"
      ],
      "conditionKeys": [],
      "dependentActions": []
    },
    {
      "name": "GetModelInvocationJob",
      "documentationUrl": "https://docs.aws.amazon.com/bedrock/latest/APIReference/API_GetModelInvocationJob.html",
      "description": "Grants permission to retrieve a model invocation job",
      "accessLevel": "Read",
      "resourceTypes": [
        "model-invocation-job*"
      ],
      "conditionKeys": [],
      "dependentActions": []
    },
    {
      "name": "GetModelInvocationLoggingConfiguration",
      "documentationUrl": "https://docs.aws.amazon.com/bedrock/latest/APIReference/API_GetModelInvocationLoggingConfiguration.html",
      "description": "Grants permission to retrieve an existing Invocation logging configuration",
      "accessLevel": "Read",
      "resourceTypes": [],
      "conditionKeys": [],
      "dependentActions": []
    },
    {
      "name": "GetPrompt",
      "documentationUrl": "https://docs.aws.amazon.com/bedrock/latest/APIReference/API_agent_GetPrompt.html",
      "description": "Grants permission to retrieve an existing prompt or its version",
      "accessLevel": "Read",
      "resourceTypes": [
        "prompt*",
        "prompt-version*"
      ],
      "conditionKeys": [],
      "dependentActions": []
    },
    {
      "name": "GetPromptRouter",
      "documentationUrl": "https://docs.aws.amazon.com/bedrock/latest/APIReference/API_GetPromptRouter.html",
      "description": "Grants permission to get the properties associated with a prompt router",
      "accessLevel": "Read",
      "resourceTypes": [
        "default-prompt-router*",
        "prompt-router*"
      ],
      "conditionKeys": [],
      "dependentActions": []
    },
    {
      "name": "GetProvisionedModelThroughput",
      "documentationUrl": "https://docs.aws.amazon.com/bedrock/latest/APIReference/API_GetProvisionedModelThroughput.html",
      "description": "Grants permission to retrieve a provisioned model throughput",
      "accessLevel": "Read",
      "resourceTypes": [
        "provisioned-model*"
      ],
      "conditionKeys": [],
      "dependentActions": []
    },
    {
      "name": "GetResourcePolicy",
      "documentationUrl": "https://docs.aws.amazon.com/bedrock/latest/APIReference/API_GetResourePolicy.html",
      "description": "Gets the resource policy document for a Bedrock resource",
      "accessLevel": "Read",
      "resourceTypes": [
        "custom-model*"
      ],
      "conditionKeys": [],
      "dependentActions": []
    },
    {
      "name": "GetSession",
      "documentationUrl": "https://docs.aws.amazon.com/bedrock/latest/APIReference/API_agent-runtime_GetSession.html",
      "description": "Grants permission to retrieve an existing session",
      "accessLevel": "Read",
      "resourceTypes": [
        "session*"
      ],
      "conditionKeys": [],
      "dependentActions": []
    },
    {
      "name": "GetUseCaseForModelAccess",
      "documentationUrl": "https://docs.aws.amazon.com/service-authorization/latest/reference/list_amazonbedrock.html",
      "description": "Grants permission to retrieve a use case for model access",
      "accessLevel": "Read",
      "resourceTypes": [],
      "conditionKeys": [],
      "dependentActions": []
    },
    {
      "name": "IngestKnowledgeBaseDocuments",
      "documentationUrl": "https://docs.aws.amazon.com/bedrock/latest/APIReference/API_agent_IngestKnowledgeBaseDocuments.html",
      "description": "Grants permission to directly ingest documents into a knowledge base",
      "accessLevel": "Write",
      "resourceTypes": [
        "knowledge-base*"
      ],
      "conditionKeys": [],
      "dependentActions": []
    },
    {
      "name": "InvokeAgent",
      "documentationUrl": "https://docs.aws.amazon.com/bedrock/latest/APIReference/API_agent-runtime_InvokeAgent.html",
      "description": "Grants permission to send user input (text-only) to the alias of an agent for Bedrock",
      "accessLevel": "Read",
      "resourceTypes": [
        "agent-alias*"
      ],
      "conditionKeys": [],
      "dependentActions": []
    },
    {
      "name": "InvokeBlueprintRecommendationAsync",
      "documentationUrl": "https://docs.aws.amazon.com/bedrock/latest/APIReference/welcome.html",
      "description": "Grants permission to invoke blueprint recommendations asynchronously",
      "accessLevel": "Write",
      "resourceTypes": [
        "data-automation-profile*"
      ],
      "conditionKeys": [],
      "dependentActions": []
    },
    {
      "name": "InvokeBuilder",
      "documentationUrl": "https://docs.aws.amazon.com/bedrock/latest/userguide/agents-create-cb.html",
      "description": "Grants permission to use the conversational builder which aids in building supported bedrock resources",
      "accessLevel": "Write",
      "resourceTypes": [],
      "conditionKeys": [],
      "dependentActions": []
    },
    {
      "name": "InvokeDataAutomationAsync",
      "documentationUrl": "https://docs.aws.amazon.com/bedrock/latest/APIReference/API_data-automation-runtime_InvokeDataAutomationAsync.html",
      "description": "Grants permission to invoke a Bedrock data automation job",
      "accessLevel": "Write",
      "resourceTypes": [
        "blueprint*",
        "data-automation-profile*",
        "data-automation-project*"
      ],
      "conditionKeys": [],
      "dependentActions": []
    },
    {
      "name": "InvokeFlow",
      "documentationUrl": "https://docs.aws.amazon.com/bedrock/latest/APIReference/API_agent-runtime_InvokeFlow.html",
      "description": "Grants permission to invoke a prompt flow with user input",
      "accessLevel": "Read",
      "resourceTypes": [
        "flow-alias*"
      ],
      "conditionKeys": [],
      "dependentActions": []
    },
    {
      "name": "InvokeInlineAgent",
      "documentationUrl": "https://docs.aws.amazon.com/bedrock/latest/APIReference/API_agent-runtime_InvokeInlineAgent.html",
      "description": "Grants permission to send user input (text-only) to the inline agent for Bedrock",
      "accessLevel": "Read",
      "resourceTypes": [],
      "conditionKeys": [],
      "dependentActions": []
    },
    {
      "name": "InvokeModel",
      "documentationUrl": "https://docs.aws.amazon.com/bedrock/latest/APIReference/API_runtime_InvokeModel.html",
      "description": "Grants permission to invoke the specified Bedrock model to run inference using the input provided in the request body",
      "accessLevel": "Read",
      "resourceTypes": [
        "application-inference-profile*",
        "async-invoke*",
        "bedrock-marketplace-model-endpoint*",
        "default-prompt-router*",
        "foundation-model*",
        "imported-model*",
        "inference-profile*",
        "prompt-router*",
        "provisioned-model*"
      ],
      "conditionKeys": [
        "bedrock:InferenceProfileArn",
        "bedrock:PromptRouterArn",
        "aws:RequestTag/${TagKey}",
        "aws:TagKeys",
        "bedrock:GuardrailIdentifier"
      ],
      "dependentActions": []
    },
    {
      "name": "InvokeModelWithResponseStream",
      "documentationUrl": "https://docs.aws.amazon.com/bedrock/latest/APIReference/API_runtime_InvokeModelWithResponseStream.html",
      "description": "Grants permission to invoke the specified Bedrock model to run inference using the input provided in the request body with streaming response",
      "accessLevel": "Read",
      "resourceTypes": [
        "application-inference-profile*",
        "bedrock-marketplace-model-endpoint*",
        "default-prompt-router*",
        "foundation-model*",
        "imported-model*",
        "inference-profile*",
        "prompt-router*",
        "provisioned-model*"
      ],
      "conditionKeys": [
        "bedrock:InferenceProfileArn",
        "bedrock:PromptRouterArn",
        "bedrock:GuardrailIdentifier"
      ],
      "dependentActions": []
    },
    {
      "name": "ListAgentActionGroups",
      "documentationUrl": "https://docs.aws.amazon.com/bedrock/latest/APIReference/API_agent_ListAgentActionGroups.html",
      "description": "Grants permission to list action groups in an agent",
      "accessLevel": "List",
      "resourceTypes": [
        "agent*"
      ],
      "conditionKeys": [],
      "dependentActions": []
    },
    {
      "name": "ListAgentAliases",
      "documentationUrl": "https://docs.aws.amazon.com/bedrock/latest/APIReference/API_agent_ListAgentAliases.html",
      "description": "Grants permission to list aliases for an agent",
      "accessLevel": "List",
      "resourceTypes": [
        "agent*"
      ],
      "conditionKeys": [],
      "dependentActions": []
    },
    {
      "name": "ListAgentCollaborators",
      "documentationUrl": "https://docs.aws.amazon.com/bedrock/latest/APIReference/API_agent_ListAgentCollaborators.html",
      "description": "Grants permission to list collaborators for an agent",
      "accessLevel": "List",
      "resourceTypes": [
        "agent*"
      ],
      "conditionKeys": [],
      "dependentActions": []
    },
    {
      "name": "ListAgentKnowledgeBases",
      "documentationUrl": "https://docs.aws.amazon.com/bedrock/latest/APIReference/API_agent_ListAgentKnowledgeBases.html",
      "description": "Grants permission to list knowledge bases associated with an agent",
      "accessLevel": "List",
      "resourceTypes": [
        "agent*"
      ],
      "conditionKeys": [],
      "dependentActions": []
    },
    {
      "name": "ListAgentVersions",
      "documentationUrl": "https://docs.aws.amazon.com/bedrock/latest/APIReference/API_agent_ListAgentVersions.html",
      "description": "Grants permission to list existing versions of an agent",
      "accessLevel": "List",
      "resourceTypes": [
        "agent*"
      ],
      "conditionKeys": [],
      "dependentActions": []
    },
    {
      "name": "ListAgents",
      "documentationUrl": "https://docs.aws.amazon.com/bedrock/latest/APIReference/API_agent_ListAgents.html",
      "description": "Grants permission to list existing agents",
      "accessLevel": "List",
      "resourceTypes": [],
      "conditionKeys": [],
      "dependentActions": []
    },
    {
      "name": "ListAsyncInvokes",
      "documentationUrl": "https://docs.aws.amazon.com/bedrock/latest/APIReference/API_ListAsyncInvokes.html",
      "description": "Grants permission to get a list of asynchronous invocations that you have submitted",
      "accessLevel": "List",
      "resourceTypes": [],
      "conditionKeys": [],
      "dependentActions": []
    },
    {
      "name": "ListBlueprints",
      "documentationUrl": "https://docs.aws.amazon.com/bedrock/latest/APIReference/API_data-automation_ListBlueprints.html",
      "description": "Grants permission to list existing blueprints for data automation",
      "accessLevel": "List",
      "resourceTypes": [
        "data-automation-project"
      ],
      "conditionKeys": [],
      "dependentActions": []
    },
    {
      "name": "ListCustomModels",
      "documentationUrl": "https://docs.aws.amazon.com/bedrock/latest/APIReference/API_ListCustomModels.html",
      "description": "Grants permission to get a list of Bedrock custom models that you have created",
      "accessLevel": "List",
      "resourceTypes": [],
      "conditionKeys": [],
      "dependentActions": []
    },
    {
      "name": "ListDataAutomationProjects",
      "documentationUrl": "https://docs.aws.amazon.com/bedrock/latest/APIReference/API_data-automation_ListDataAutomationProjects.html",
      "description": "Grants permission to list existing data automation projects",
      "accessLevel": "List",
      "resourceTypes": [
        "blueprint"
      ],
      "conditionKeys": [],
      "dependentActions": []
    },
    {
      "name": "ListDataSources",
      "documentationUrl": "https://docs.aws.amazon.com/bedrock/latest/APIReference/API_agent_ListDataSources.html",
      "description": "Grants permission to list existing data sources in an knowledge base",
      "accessLevel": "List",
      "resourceTypes": [
        "knowledge-base*"
      ],
      "conditionKeys": [],
      "dependentActions": []
    },
    {
      "name": "ListEvaluationJobs",
      "documentationUrl": "https://docs.aws.amazon.com/bedrock/latest/APIReference/API_ListEvaluationJobs.html",
      "description": "Grants permission to get the list of evaluation jobs that you have submitted",
      "accessLevel": "List",
      "resourceTypes": [],
      "conditionKeys": [],
      "dependentActions": []
    },
    {
      "name": "ListFlowAliases",
      "documentationUrl": "https://docs.aws.amazon.com/bedrock/latest/APIReference/API_agent_ListFlowAliases.html",
      "description": "Grants permission to list existing aliases of a prompt flow",
      "accessLevel": "List",
      "resourceTypes": [
        "flow*"
      ],
      "conditionKeys": [],
      "dependentActions": []
    },
    {
      "name": "ListFlowVersions",
      "documentationUrl": "https://docs.aws.amazon.com/bedrock/latest/APIReference/API_agent_ListFlowVersions.html",
      "description": "Grants permission to list existing versions of a prompt flow",
      "accessLevel": "List",
      "resourceTypes": [
        "flow*"
      ],
      "conditionKeys": [],
      "dependentActions": []
    },
    {
      "name": "ListFlows",
      "documentationUrl": "https://docs.aws.amazon.com/bedrock/latest/APIReference/API_agent_ListFlows.html",
      "description": "Grants permission to list existing prompt flows",
      "accessLevel": "List",
      "resourceTypes": [],
      "conditionKeys": [],
      "dependentActions": []
    },
    {
      "name": "ListFoundationModelAgreementOffers",
      "documentationUrl": "https://docs.aws.amazon.com/service-authorization/latest/reference/list_amazonbedrock.html",
      "description": "Grants permission to get a list of foundation model agreement offers",
      "accessLevel": "List",
      "resourceTypes": [],
      "conditionKeys": [],
      "dependentActions": []
    },
    {
      "name": "ListFoundationModels",
      "documentationUrl": "https://docs.aws.amazon.com/bedrock/latest/APIReference/API_ListFoundationModels.html",
      "description": "Grants permission to list Bedrock foundation models that you can use",
      "accessLevel": "List",
      "resourceTypes": [],
      "conditionKeys": [],
      "dependentActions": []
    },
    {
      "name": "ListGuardrails",
      "documentationUrl": "https://docs.aws.amazon.com/bedrock/latest/APIReference/welcome.html",
      "description": "Grants permission to list guardrails or its versions",
      "accessLevel": "List",
      "resourceTypes": [
        "guardrail"
      ],
      "conditionKeys": [],
      "dependentActions": []
    },
    {
      "name": "ListImportedModels",
      "documentationUrl": "https://docs.aws.amazon.com/bedrock/latest/APIReference/API_ListImportedModels.html",
      "description": "Grants permission to get list of Bedrock imported models",
      "accessLevel": "List",
      "resourceTypes": [],
      "conditionKeys": [],
      "dependentActions": []
    },
    {
      "name": "ListInferenceProfiles",
      "documentationUrl": "https://docs.aws.amazon.com/bedrock/latest/APIReference/API_ListInferenceProfiles.html",
      "description": "Grants permission to list inference profiles that you can use",
      "accessLevel": "List",
      "resourceTypes": [],
      "conditionKeys": [],
      "dependentActions": []
    },
    {
      "name": "ListIngestionJobs",
      "documentationUrl": "https://docs.aws.amazon.com/bedrock/latest/APIReference/API_agent_ListIngestionJobs.html",
      "description": "Grants permission to list ingestion jobs in a data source",
      "accessLevel": "List",
      "resourceTypes": [
        "knowledge-base*"
      ],
      "conditionKeys": [],
      "dependentActions": []
    },
    {
      "name": "ListInvocationSteps",
      "documentationUrl": "https://docs.aws.amazon.com/bedrock/latest/APIReference/API_agent-runtime_ListInvocationSteps.html",
      "description": "Grants permission to get list of invocation step from a session",
      "accessLevel": "List",
      "resourceTypes": [
        "session*"
      ],
      "conditionKeys": [],
      "dependentActions": []
    },
    {
      "name": "ListInvocations",
      "documentationUrl": "https://docs.aws.amazon.com/bedrock/latest/APIReference/API_agent-runtime_ListInvocations.html",
      "description": "Grants permission to list invocations in a session",
      "accessLevel": "List",
      "resourceTypes": [
        "session*"
      ],
      "conditionKeys": [],
      "dependentActions": []
    },
    {
      "name": "ListKnowledgeBaseDocuments",
      "documentationUrl": "https://docs.aws.amazon.com/bedrock/latest/APIReference/API_agent_ListKnowledgeBaseDocuments.html",
      "description": "Grants permission to list documents in a knowledge base",
      "accessLevel": "List",
      "resourceTypes": [
        "knowledge-base*"
      ],
      "conditionKeys": [],
      "dependentActions": []
    },
    {
      "name": "ListKnowledgeBases",
      "documentationUrl": "https://docs.aws.amazon.com/bedrock/latest/APIReference/API_agent_ListKnowledgeBases.html",
      "description": "Grants permission to list existing knowledge bases",
      "accessLevel": "List",
      "resourceTypes": [],
      "conditionKeys": [],
      "dependentActions": []
    },
    {
      "name": "ListMarketplaceModelEndpoints",
      "documentationUrl": "API_ListMarketplaceModelEndpoints",
      "description": "Grants permission to list marketplace model endpoints that you can use",
      "accessLevel": "Read",
      "resourceTypes": [],
      "conditionKeys": [],
      "dependentActions": []
    },
    {
      "name": "ListModelCopyJobs",
      "documentationUrl": "https://docs.aws.amazon.com/bedrock/latest/APIReference/API_ListModelCopyJobs.html",
      "description": "Grants permission to get the list of model copy jobs that you have submitted",
      "accessLevel": "List",
      "resourceTypes": [],
      "conditionKeys": [],
      "dependentActions": []
    },
    {
      "name": "ListModelCustomizationJobs",
      "documentationUrl": "https://docs.aws.amazon.com/bedrock/latest/APIReference/API_ListModelCustomizationJobs.html",
      "description": "Grants permission to get the list of model customization jobs that you have submitted",
      "accessLevel": "List",
      "resourceTypes": [],
      "conditionKeys": [],
      "dependentActions": []
    },
    {
      "name": "ListModelEvaluationJobs",
      "documentationUrl": "https://docs.aws.amazon.com/bedrock/latest/APIReference/API_ListModelEvaluationJobs.html",
      "description": "Grants permission to get the list of model evaluation jobs that you have submitted",
      "accessLevel": "List",
      "resourceTypes": [],
      "conditionKeys": [],
      "dependentActions": []
    },
    {
      "name": "ListModelImportJobs",
      "documentationUrl": "https://docs.aws.amazon.com/bedrock/latest/APIReference/API_ListModelImportJobs.html",
      "description": "Grants permission to get list of model import jobs",
      "accessLevel": "List",
      "resourceTypes": [],
      "conditionKeys": [],
      "dependentActions": []
    },
    {
      "name": "ListModelInvocationJobs",
      "documentationUrl": "https://docs.aws.amazon.com/bedrock/latest/APIReference/API_ListModelInvocationJobs.html",
      "description": "Grants permission to list model invocation jobs that you created earlier",
      "accessLevel": "List",
      "resourceTypes": [],
      "conditionKeys": [],
      "dependentActions": []
    },
    {
      "name": "ListPromptRouters",
      "documentationUrl": "https://docs.aws.amazon.com/bedrock/latest/APIReference/API_ListPromptRouters.html",
      "description": "Grants permission to list prompt routers that you can use",
      "accessLevel": "List",
      "resourceTypes": [],
      "conditionKeys": [],
      "dependentActions": []
    },
    {
      "name": "ListPrompts",
      "documentationUrl": "https://docs.aws.amazon.com/bedrock/latest/APIReference/API_agent_ListPrompts.html",
      "description": "Grants permission to list existing prompts",
      "accessLevel": "List",
      "resourceTypes": [
        "prompt"
      ],
      "conditionKeys": [],
      "dependentActions": []
    },
    {
      "name": "ListProvisionedModelThroughputs",
      "documentationUrl": "https://docs.aws.amazon.com/bedrock/latest/APIReference/API_ListProvisionedModelThroughputs.html",
      "description": "Grants permission to list provisioned model throughputs that you created earlier",
      "accessLevel": "List",
      "resourceTypes": [],
      "conditionKeys": [],
      "dependentActions": []
    },
    {
      "name": "ListSessions",
      "documentationUrl": "https://docs.aws.amazon.com/bedrock/latest/APIReference/API_agent-runtime_ListSessions.html",
      "description": "Grants permission to list existing sessions",
      "accessLevel": "List",
      "resourceTypes": [],
      "conditionKeys": [],
      "dependentActions": []
    },
    {
      "name": "ListTagsForResource",
      "documentationUrl": "https://docs.aws.amazon.com/bedrock/latest/APIReference/API_ListTagsForResource.html",
      "description": "Grants permission to list tags for a Bedrock resource",
      "accessLevel": "Read",
      "resourceTypes": [
        "agent*",
        "agent-alias*",
        "application-inference-profile*",
        "async-invoke*",
        "blueprint*",
        "custom-model*",
        "data-automation-invocation-job*",
        "data-automation-project*",
        "evaluation-job*",
        "flow*",
        "flow-alias*",
        "guardrail*",
        "imported-model*",
        "knowledge-base*",
        "model-copy-job*",
        "model-customization-job*",
        "model-evaluation-job*",
        "model-import-job*",
        "model-invocation-job*",
        "prompt*",
        "prompt-router*",
        "prompt-version*",
        "provisioned-model*",
        "session*"
      ],
      "conditionKeys": [],
      "dependentActions": []
    },
    {
      "name": "OptimizePrompt",
      "documentationUrl": "https://docs.aws.amazon.com/bedrock/latest/APIReference/API_agent-runtime_OptimizePrompt.html",
      "description": "Grants permission to optimize a prompt with user input",
      "accessLevel": "Read",
      "resourceTypes": [],
      "conditionKeys": [],
      "dependentActions": []
    },
    {
      "name": "PrepareAgent",
      "documentationUrl": "https://docs.aws.amazon.com/bedrock/latest/APIReference/API_agent_PrepareAgent.html",
      "description": "Grants permission to prepare an existing agent to receive runtime requests",
      "accessLevel": "Write",
      "resourceTypes": [
        "agent*"
      ],
      "conditionKeys": [],
      "dependentActions": []
    },
    {
      "name": "PrepareFlow",
      "documentationUrl": "https://docs.aws.amazon.com/bedrock/latest/APIReference/API_agent_PrepareFlow.html",
      "description": "Grants permission to apply the latest changes made to a prompt flow, so that they are reflected at runtime",
      "accessLevel": "Write",
      "resourceTypes": [
        "flow*"
      ],
      "conditionKeys": [],
      "dependentActions": []
    },
    {
      "name": "PutFoundationModelEntitlement",
      "documentationUrl": "https://docs.aws.amazon.com/service-authorization/latest/reference/list_amazonbedrock.html",
      "description": "Grants permission to put entitlement to access a foundation model",
      "accessLevel": "Write",
      "resourceTypes": [],
      "conditionKeys": [],
      "dependentActions": []
    },
    {
      "name": "PutInvocationStep",
      "documentationUrl": "https://docs.aws.amazon.com/bedrock/latest/APIReference/API_agent-runtime_PutInvocationStep.html",
      "description": "Grants permission to put an invocation step into an invocation in session",
      "accessLevel": "Write",
      "resourceTypes": [
        "session*"
      ],
      "conditionKeys": [],
      "dependentActions": []
    },
    {
      "name": "PutModelInvocationLoggingConfiguration",
      "documentationUrl": "https://docs.aws.amazon.com/bedrock/latest/APIReference/API_PutModelInvocationLoggingConfiguration.html",
      "description": "Grants permission to create an existing Invocation logging configuration",
      "accessLevel": "Write",
      "resourceTypes": [],
      "conditionKeys": [],
      "dependentActions": []
    },
    {
      "name": "PutResourcePolicy",
      "documentationUrl": "https://docs.aws.amazon.com/bedrock/latest/APIReference/API_PutResourcePolicy.html",
      "description": "Adds a resource policy for a Bedrock resource",
      "accessLevel": "Write",
      "resourceTypes": [
        "custom-model*"
      ],
      "conditionKeys": [
        "aws:RequestTag/${TagKey}",
        "aws:TagKeys"
      ],
      "dependentActions": []
    },
    {
      "name": "PutUseCaseForModelAccess",
      "documentationUrl": "https://docs.aws.amazon.com/service-authorization/latest/reference/list_amazonbedrock.html",
      "description": "Grants permission to put a use case for model access",
      "accessLevel": "Write",
      "resourceTypes": [],
      "conditionKeys": [],
      "dependentActions": []
    },
    {
      "name": "RegisterMarketplaceModelEndpoint",
      "documentationUrl": "API_RegisterMarketplaceModelEndpoint",
      "description": "Grants permission to register a sagemaker endpoint as a marketplace model endpoint",
      "accessLevel": "Write",
      "resourceTypes": [
        "bedrock-marketplace-model-endpoint*"
      ],
      "conditionKeys": [],
      "dependentActions": []
    },
    {
      "name": "RenderPrompt",
      "documentationUrl": "https://docs.aws.amazon.com/bedrock/latest/APIReference/welcome.html",
      "description": "Grants permission to render an existing prompt or its version",
      "accessLevel": "Read",
      "resourceTypes": [
        "prompt*",
        "prompt-version*"
      ],
      "conditionKeys": [],
      "dependentActions": []
    },
    {
      "name": "Rerank",
      "documentationUrl": "https://docs.aws.amazon.com/bedrock/latest/APIReference/welcome.html",
      "description": "Grants permission to rank documents based on user input",
      "accessLevel": "Write",
      "resourceTypes": [],
      "conditionKeys": [],
      "dependentActions": []
    },
    {
      "name": "Retrieve",
      "documentationUrl": "https://docs.aws.amazon.com/bedrock/latest/APIReference/welcome.html",
      "description": "Grants permission to retrieve ingested data from a knowledge base",
      "accessLevel": "Read",
      "resourceTypes": [
        "knowledge-base*"
      ],
      "conditionKeys": [],
      "dependentActions": []
    },
    {
      "name": "RetrieveAndGenerate",
      "documentationUrl": "https://docs.aws.amazon.com/bedrock/latest/APIReference/welcome.html",
      "description": "Grants permission to send user input to perform retrieval and generation",
      "accessLevel": "Write",
      "resourceTypes": [],
      "conditionKeys": [],
      "dependentActions": []
    },
    {
      "name": "StartIngestionJob",
      "documentationUrl": "https://docs.aws.amazon.com/bedrock/latest/APIReference/API_agent_StartIngestionJob.html",
      "description": "Grants permission to start an ingestion job",
      "accessLevel": "Write",
      "resourceTypes": [
        "knowledge-base*"
      ],
      "conditionKeys": [],
      "dependentActions": []
    },
    {
      "name": "StopEvaluationJob",
      "documentationUrl": "https://docs.aws.amazon.com/bedrock/latest/APIReference/API_StopEvaluationJob.html",
      "description": "Grants permission to stop a evaluation job while in progress",
      "accessLevel": "Write",
      "resourceTypes": [
        "evaluation-job*"
      ],
      "conditionKeys": [],
      "dependentActions": []
    },
    {
      "name": "StopIngestionJob",
      "documentationUrl": "https://docs.aws.amazon.com/bedrock/latest/APIReference/API_agent_StopIngestionJob.html",
      "description": "Grants permission to stop an ingestion job",
      "accessLevel": "Write",
      "resourceTypes": [
        "knowledge-base*"
      ],
      "conditionKeys": [],
      "dependentActions": []
    },
    {
      "name": "StopModelCustomizationJob",
      "documentationUrl": "https://docs.aws.amazon.com/bedrock/latest/APIReference/API_StopModelCustomizationJob.html",
      "description": "Grants permission to stop a Bedrock model customization job while in progress",
      "accessLevel": "Write",
      "resourceTypes": [
        "model-customization-job*"
      ],
      "conditionKeys": [],
      "dependentActions": []
    },
    {
      "name": "StopModelInvocationJob",
      "documentationUrl": "https://docs.aws.amazon.com/bedrock/latest/APIReference/API_StopModelInvocationJob.html",
      "description": "Grants permission to stop a model invocation job that you started earlier",
      "accessLevel": "Write",
      "resourceTypes": [
        "model-invocation-job*"
      ],
      "conditionKeys": [],
      "dependentActions": []
    },
    {
      "name": "TagResource",
      "documentationUrl": "https://docs.aws.amazon.com/bedrock/latest/APIReference/API_TagResource.html",
      "description": "Grants permission to Tag a Bedrock resource",
      "accessLevel": "Tagging",
      "resourceTypes": [
        "agent",
        "agent-alias",
        "application-inference-profile",
        "async-invoke",
        "blueprint",
        "custom-model",
        "data-automation-invocation-job",
        "data-automation-project",
        "evaluation-job",
        "flow",
        "flow-alias",
        "guardrail",
        "imported-model",
        "knowledge-base",
        "model-copy-job",
        "model-customization-job",
        "model-evaluation-job",
        "model-import-job",
        "model-invocation-job",
        "prompt",
        "prompt-router",
        "prompt-version",
        "provisioned-model",
        "session"
      ],
      "conditionKeys": [
        "aws:TagKeys",
        "aws:RequestTag/${TagKey}"
      ],
      "dependentActions": []
    },
    {
      "name": "UntagResource",
      "documentationUrl": "https://docs.aws.amazon.com/bedrock/latest/APIReference/API_UntagResource.html",
      "description": "Grants permission to Untag a Bedrock resource",
      "accessLevel": "Tagging",
      "resourceTypes": [
        "agent",
        "agent-alias",
        "application-inference-profile",
        "async-invoke",
        "blueprint",
        "custom-model",
        "data-automation-invocation-job",
        "data-automation-project",
        "evaluation-job",
        "flow",
        "flow-alias",
        "guardrail",
        "imported-model",
        "knowledge-base",
        "model-copy-job",
        "model-customization-job",
        "model-evaluation-job",
        "model-import-job",
        "model-invocation-job",
        "prompt",
        "prompt-router",
        "prompt-version",
        "provisioned-model",
        "session"
      ],
      "conditionKeys": [
        "aws:TagKeys"
      ],
      "dependentActions": []
    },
    {
      "name": "UpdateAgent",
      "documentationUrl": "https://docs.aws.amazon.com/bedrock/latest/APIReference/API_agent_UpdateAgent.html",
      "description": "Grants permission to update an existing agent",
      "accessLevel": "Write",
      "resourceTypes": [
        "agent*"
      ],
      "conditionKeys": [],
      "dependentActions": []
    },
    {
      "name": "UpdateAgentActionGroup",
      "documentationUrl": "https://docs.aws.amazon.com/bedrock/latest/APIReference/API_agent_UpdateAgentActionGroup.html",
      "description": "Grants permission to update an existing action group",
      "accessLevel": "Write",
      "resourceTypes": [
        "agent*"
      ],
      "conditionKeys": [],
      "dependentActions": []
    },
    {
      "name": "UpdateAgentAlias",
      "documentationUrl": "https://docs.aws.amazon.com/bedrock/latest/APIReference/API_agent_UpdateAgentAlias.html",
      "description": "Grants permission to update an existing alias",
      "accessLevel": "Write",
      "resourceTypes": [
        "agent-alias*"
      ],
      "conditionKeys": [],
      "dependentActions": []
    },
    {
      "name": "UpdateAgentCollaborator",
      "documentationUrl": "https://docs.aws.amazon.com/bedrock/latest/APIReference/API_agent_UpdateAgentCollaborator.html",
      "description": "Grants permission to update an existing collaborator",
      "accessLevel": "Write",
      "resourceTypes": [
        "agent*"
      ],
      "conditionKeys": [],
      "dependentActions": []
    },
    {
      "name": "UpdateAgentKnowledgeBase",
      "documentationUrl": "https://docs.aws.amazon.com/bedrock/latest/APIReference/API_agent_UpdateAgentKnowledgeBase.html",
      "description": "Grants permission to update a knowledge base associated with an agent",
      "accessLevel": "Write",
      "resourceTypes": [
        "agent*",
        "knowledge-base*"
      ],
      "conditionKeys": [],
      "dependentActions": []
    },
    {
      "name": "UpdateBlueprint",
      "documentationUrl": "https://docs.aws.amazon.com/bedrock/latest/APIReference/API_data-automation_UpdateBlueprint.html",
      "description": "Grants permission to update a blueprint for data automation",
      "accessLevel": "Write",
      "resourceTypes": [
        "blueprint*"
      ],
      "conditionKeys": [],
      "dependentActions": []
    },
    {
      "name": "UpdateDataAutomationProject",
      "documentationUrl": "https://docs.aws.amazon.com/bedrock/latest/APIReference/API_data-automation_UpdateDataAutomationProject.html",
      "description": "Grants permission to update a data automation project",
      "accessLevel": "Write",
      "resourceTypes": [
        "data-automation-project*",
        "blueprint"
      ],
      "conditionKeys": [],
      "dependentActions": []
    },
    {
      "name": "UpdateDataSource",
      "documentationUrl": "https://docs.aws.amazon.com/bedrock/latest/APIReference/API_agent_UpdateDataSource.html",
      "description": "Grants permission to update a data source",
      "accessLevel": "Write",
      "resourceTypes": [
        "knowledge-base*"
      ],
      "conditionKeys": [],
      "dependentActions": []
    },
    {
      "name": "UpdateFlow",
      "documentationUrl": "https://docs.aws.amazon.com/bedrock/latest/APIReference/API_agent_UpdateFlow.html",
      "description": "Grants permission to update a prompt flow",
      "accessLevel": "Write",
      "resourceTypes": [
        "flow*"
      ],
      "conditionKeys": [],
      "dependentActions": []
    },
    {
      "name": "UpdateFlowAlias",
      "documentationUrl": "https://docs.aws.amazon.com/bedrock/latest/APIReference/API_agent_UpdateFlowAlias.html",
      "description": "Grants permission to update the configuration of an alias of a prompt flow",
      "accessLevel": "Write",
      "resourceTypes": [
        "flow-alias*"
      ],
      "conditionKeys": [],
      "dependentActions": []
    },
    {
      "name": "UpdateGuardrail",
      "documentationUrl": "https://docs.aws.amazon.com/bedrock/latest/APIReference/welcome.html",
      "description": "Grants permission to update a guardrail",
      "accessLevel": "Write",
      "resourceTypes": [
        "guardrail*"
      ],
      "conditionKeys": [],
      "dependentActions": []
    },
    {
      "name": "UpdateKnowledgeBase",
      "documentationUrl": "https://docs.aws.amazon.com/bedrock/latest/APIReference/API_agent_UpdateKnowledgeBase.html",
      "description": "Grants permission to update a knowledge base",
      "accessLevel": "Write",
      "resourceTypes": [
        "knowledge-base*"
      ],
      "conditionKeys": [],
      "dependentActions": []
    },
    {
      "name": "UpdateMarketplaceModelEndpoint",
      "documentationUrl": "API_UpdateMarketplaceModelEndpoint",
      "description": "Grants permission to update a marketplace model endpoint",
      "accessLevel": "Write",
      "resourceTypes": [
        "bedrock-marketplace-model-endpoint*"
      ],
      "conditionKeys": [],
      "dependentActions": []
    },
    {
      "name": "UpdatePrompt",
      "documentationUrl": "https://docs.aws.amazon.com/bedrock/latest/APIReference/API_agent_UpdatePrompt.html",
      "description": "Grants permission to update a prompt",
      "accessLevel": "Write",
      "resourceTypes": [
        "prompt*"
      ],
      "conditionKeys": [],
      "dependentActions": []
    },
    {
      "name": "UpdateProvisionedModelThroughput",
      "documentationUrl": "https://docs.aws.amazon.com/bedrock/latest/APIReference/API_UpdateProvisionedModelThroughput.html",
      "description": "Grants permission to update a provisioned model throughput that you created earlier",
      "accessLevel": "Write",
      "resourceTypes": [
        "custom-model*",
        "foundation-model*",
        "provisioned-model*"
      ],
      "conditionKeys": [],
      "dependentActions": []
    },
    {
      "name": "UpdateSession",
      "documentationUrl": "https://docs.aws.amazon.com/bedrock/latest/APIReference/API_agent-runtime_UpdateSession.html",
      "description": "Grants permission to update an existing session",
      "accessLevel": "Write",
      "resourceTypes": [
        "session*"
      ],
      "conditionKeys": [],
      "dependentActions": []
    },
    {
      "name": "ValidateFlowDefinition",
      "documentationUrl": "https://docs.aws.amazon.com/bedrock/latest/APIReference/API_agent_ValidateFlowDefinition.html",
      "description": "Grants permission to validate prompt flow definitions",
      "accessLevel": "Read",
      "resourceTypes": [],
      "conditionKeys": [],
      "dependentActions": []
    }
  ]
}