{
  "serviceName": "AWS IAM Identity Center (successor to AWS Single Sign-On) directory",
  "servicePrefix": "sso-directory",
  "url": "https://docs.aws.amazon.com/service-authorization/latest/reference/./list_awsiamidentitycentersuccessortoawssinglesign-ondirectory.html",
  "actions": [
    {
      "name": "AddMemberToGroup",
      "documentationUrl": "https://docs.aws.amazon.com/singlesignon/latest/IdentityStoreAPIReference/API_CreateGroupMembership.html",
      "description": "Grants permission to add a member to a group in the directory that AWS IAM Identity Center provides by default",
      "accessLevel": "Write",
      "resourceTypes": [],
      "conditionKeys": [],
      "dependentActions": []
    },
    {
      "name": "CompleteVirtualMfaDeviceRegistration",
      "documentationUrl": "https://docs.aws.amazon.com/singlesignon/latest/userguide/iam-auth-access-using-id-policies.html#policyexample",
      "description": "Grants permission to complete the creation process of a virtual MFA device",
      "accessLevel": "Write",
      "resourceTypes": [],
      "conditionKeys": [],
      "dependentActions": []
    },
    {
      "name": "CompleteWebAuthnDeviceRegistration",
      "documentationUrl": "https://docs.aws.amazon.com/singlesignon/latest/userguide/iam-auth-access-using-id-policies.html#policyexample",
      "description": "Grants permission to complete the registration process of a WebAuthn device",
      "accessLevel": "Write",
      "resourceTypes": [],
      "conditionKeys": [],
      "dependentActions": []
    },
    {
      "name": "CreateAlias",
      "documentationUrl": "https://docs.aws.amazon.com/singlesignon/latest/userguide/iam-auth-access-using-id-policies.html#policyexample",
      "description": "Grants permission to create an alias for the directory that AWS IAM Identity Center provides by default",
      "accessLevel": "Write",
      "resourceTypes": [],
      "conditionKeys": [],
      "dependentActions": []
    },
    {
      "name": "CreateBearerToken",
      "documentationUrl": "https://docs.aws.amazon.com/singlesignon/latest/userguide/iam-auth-access-using-id-policies.html#policyexample",
      "description": "Grants permission to create a bearer token for a given provisioning tenant",
      "accessLevel": "Write",
      "resourceTypes": [],
      "conditionKeys": [],
      "dependentActions": []
    },
    {
      "name": "CreateExternalIdPConfigurationForDirectory",
      "documentationUrl": "https://docs.aws.amazon.com/singlesignon/latest/userguide/iam-auth-access-using-id-policies.html#policyexample",
      "description": "Grants permission to create an External Identity Provider configuration for the directory",
      "accessLevel": "Write",
      "resourceTypes": [],
      "conditionKeys": [],
      "dependentActions": []
    },
    {
      "name": "CreateGroup",
      "documentationUrl": "https://docs.aws.amazon.com/singlesignon/latest/IdentityStoreAPIReference/API_CreateGroup.html",
      "description": "Grants permission to create a group in the directory that AWS IAM Identity Center provides by default",
      "accessLevel": "Write",
      "resourceTypes": [],
      "conditionKeys": [],
      "dependentActions": []
    },
    {
      "name": "CreateProvisioningTenant",
      "documentationUrl": "https://docs.aws.amazon.com/singlesignon/latest/userguide/iam-auth-access-using-id-policies.html#policyexample",
      "description": "Grants permission to create a provisioning tenant for a given directory",
      "accessLevel": "Write",
      "resourceTypes": [],
      "conditionKeys": [],
      "dependentActions": []
    },
    {
      "name": "CreateUser",
      "documentationUrl": "https://docs.aws.amazon.com/singlesignon/latest/IdentityStoreAPIReference/API_CreateUser.html",
      "description": "Grants permission to create a user in the directory that AWS IAM Identity Center provides by default",
      "accessLevel": "Write",
      "resourceTypes": [],
      "conditionKeys": [],
      "dependentActions": []
    },
    {
      "name": "DeleteBearerToken",
      "documentationUrl": "https://docs.aws.amazon.com/singlesignon/latest/userguide/iam-auth-access-using-id-policies.html#policyexample",
      "description": "Grants permission to delete a bearer token",
      "accessLevel": "Write",
      "resourceTypes": [],
      "conditionKeys": [],
      "dependentActions": []
    },
    {
      "name": "DeleteExternalIdPCertificate",
      "documentationUrl": "https://docs.aws.amazon.com/singlesignon/latest/userguide/iam-auth-access-using-id-policies.html#policyexample",
      "description": "Grants permission to delete the given external IdP certificate",
      "accessLevel": "Write",
      "resourceTypes": [],
      "conditionKeys": [],
      "dependentActions": []
    },
    {
      "name": "DeleteExternalIdPConfigurationForDirectory",
      "documentationUrl": "https://docs.aws.amazon.com/singlesignon/latest/userguide/iam-auth-access-using-id-policies.html#policyexample",
      "description": "Grants permission to delete an External Identity Provider configuration associated with the directory",
      "accessLevel": "Write",
      "resourceTypes": [],
      "conditionKeys": [],
      "dependentActions": []
    },
    {
      "name": "DeleteGroup",
      "documentationUrl": "https://docs.aws.amazon.com/singlesignon/latest/IdentityStoreAPIReference/API_DeleteGroup.html",
      "description": "Grants permission to delete a group from the directory that AWS IAM Identity Center provides by default",
      "accessLevel": "Write",
      "resourceTypes": [],
      "conditionKeys": [],
      "dependentActions": []
    },
    {
      "name": "DeleteMfaDeviceForUser",
      "documentationUrl": "https://docs.aws.amazon.com/singlesignon/latest/userguide/iam-auth-access-using-id-policies.html#policyexample",
      "description": "Grants permission to delete a MFA device by device name for a given user",
      "accessLevel": "Write",
      "resourceTypes": [],
      "conditionKeys": [],
      "dependentActions": []
    },
    {
      "name": "DeleteProvisioningTenant",
      "documentationUrl": "https://docs.aws.amazon.com/singlesignon/latest/userguide/iam-auth-access-using-id-policies.html#policyexample",
      "description": "Grants permission to delete the provisioning tenant",
      "accessLevel": "Write",
      "resourceTypes": [],
      "conditionKeys": [],
      "dependentActions": []
    },
    {
      "name": "DeleteUser",
      "documentationUrl": "https://docs.aws.amazon.com/singlesignon/latest/IdentityStoreAPIReference/API_DeleteUser.html",
      "description": "Grants permission to delete a user from the directory that AWS IAM Identity Center provides by default",
      "accessLevel": "Write",
      "resourceTypes": [],
      "conditionKeys": [],
      "dependentActions": []
    },
    {
      "name": "DescribeDirectory",
      "documentationUrl": "https://docs.aws.amazon.com/singlesignon/latest/userguide/iam-auth-access-using-id-policies.html#policyexample",
      "description": "Grants permission to retrieve information about the directory that AWS IAM Identity Center provides by default",
      "accessLevel": "Read",
      "resourceTypes": [],
      "conditionKeys": [],
      "dependentActions": []
    },
    {
      "name": "DescribeGroup",
      "documentationUrl": "https://docs.aws.amazon.com/singlesignon/latest/IdentityStoreAPIReference/API_DescribeGroup.html",
      "description": "Grants permission to query the group data, not including user and group members",
      "accessLevel": "Read",
      "resourceTypes": [],
      "conditionKeys": [],
      "dependentActions": []
    },
    {
      "name": "DescribeGroups",
      "documentationUrl": "https://docs.aws.amazon.com/singlesignon/latest/IdentityStoreAPIReference/API_DescribeGroup.html",
      "description": "Grants permission to retrieve information about groups from the directory that AWS IAM Identity Center provides by default",
      "accessLevel": "Read",
      "resourceTypes": [],
      "conditionKeys": [],
      "dependentActions": []
    },
    {
      "name": "DescribeProvisioningTenant",
      "documentationUrl": "https://docs.aws.amazon.com/singlesignon/latest/userguide/iam-auth-access-using-id-policies.html#policyexample",
      "description": "Grants permission to describes the provisioning tenant",
      "accessLevel": "Read",
      "resourceTypes": [],
      "conditionKeys": [],
      "dependentActions": []
    },
    {
      "name": "DescribeUser",
      "documentationUrl": "https://docs.aws.amazon.com/singlesignon/latest/IdentityStoreAPIReference/API_DescribeUser.html",
      "description": "Grants permission to retrieve information about a user from the directory that AWS IAM Identity Center provides by default",
      "accessLevel": "Read",
      "resourceTypes": [],
      "conditionKeys": [],
      "dependentActions": []
    },
    {
      "name": "DescribeUserByUniqueAttribute",
      "documentationUrl": "https://docs.aws.amazon.com/singlesignon/latest/userguide/iam-auth-access-using-id-policies.html#policyexample",
      "description": "Grants permission to describe user with a valid unique attribute represented for the user",
      "accessLevel": "Read",
      "resourceTypes": [],
      "conditionKeys": [],
      "dependentActions": []
    },
    {
      "name": "DescribeUsers",
      "documentationUrl": "https://docs.aws.amazon.com/singlesignon/latest/IdentityStoreAPIReference/API_DescribeUser.html",
      "description": "Grants permission to retrieve information about user from the directory that AWS IAM Identity Center provides by default",
      "accessLevel": "Read",
      "resourceTypes": [],
      "conditionKeys": [],
      "dependentActions": []
    },
    {
      "name": "DisableExternalIdPConfigurationForDirectory",
      "documentationUrl": "https://docs.aws.amazon.com/singlesignon/latest/userguide/iam-auth-access-using-id-policies.html#policyexample",
      "description": "Grants permission to disable authentication of end users with an External Identity Provider",
      "accessLevel": "Write",
      "resourceTypes": [],
      "conditionKeys": [],
      "dependentActions": []
    },
    {
      "name": "DisableUser",
      "documentationUrl": "https://docs.aws.amazon.com/singlesignon/latest/userguide/iam-auth-access-using-id-policies.html#policyexample",
      "description": "Grants permission to deactivate a user in the directory that AWS IAM Identity Center provides by default",
      "accessLevel": "Write",
      "resourceTypes": [],
      "conditionKeys": [],
      "dependentActions": []
    },
    {
      "name": "EnableExternalIdPConfigurationForDirectory",
      "documentationUrl": "https://docs.aws.amazon.com/singlesignon/latest/userguide/iam-auth-access-using-id-policies.html#policyexample",
      "description": "Grants permission to enable authentication of end users with an External Identity Provider",
      "accessLevel": "Write",
      "resourceTypes": [],
      "conditionKeys": [],
      "dependentActions": []
    },
    {
      "name": "EnableUser",
      "documentationUrl": "https://docs.aws.amazon.com/singlesignon/latest/userguide/iam-auth-access-using-id-policies.html#policyexample",
      "description": "Grants permission to activate user in the directory that AWS IAM Identity Center provides by default",
      "accessLevel": "Write",
      "resourceTypes": [],
      "conditionKeys": [],
      "dependentActions": []
    },
    {
      "name": "GetAWSSPConfigurationForDirectory",
      "documentationUrl": "https://docs.aws.amazon.com/singlesignon/latest/userguide/iam-auth-access-using-id-policies.html#policyexample",
      "description": "Grants permission to retrieve the AWS IAM Identity Center Service Provider configurations for the directory",
      "accessLevel": "Read",
      "resourceTypes": [],
      "conditionKeys": [],
      "dependentActions": []
    },
    {
      "name": "GetGroupId",
      "documentationUrl": "https://docs.aws.amazon.com/singlesignon/latest/IdentityStoreAPIReference/API_GetGroupId.html",
      "description": "Grants permission to retrieve ID information about group from the directory that AWS IAM Identity Center provides by default",
      "accessLevel": "Read",
      "resourceTypes": [],
      "conditionKeys": [],
      "dependentActions": []
    },
    {
      "name": "GetUserId",
      "documentationUrl": "https://docs.aws.amazon.com/singlesignon/latest/IdentityStoreAPIReference/API_GetUserId.html",
      "description": "Grants permission to retrieve ID information about user from the directory that AWS IAM Identity Center provides by default",
      "accessLevel": "Read",
      "resourceTypes": [],
      "conditionKeys": [],
      "dependentActions": []
    },
    {
      "name": "GetUserPoolInfo",
      "documentationUrl": "https://docs.aws.amazon.com/singlesignon/latest/userguide/iam-auth-access-using-id-policies.html#policyexample",
      "description": "(Deprecated) Grants permission to get UserPool Info",
      "accessLevel": "Read",
      "resourceTypes": [],
      "conditionKeys": [],
      "dependentActions": []
    },
    {
      "name": "ImportExternalIdPCertificate",
      "documentationUrl": "https://docs.aws.amazon.com/singlesignon/latest/userguide/iam-auth-access-using-id-policies.html#policyexample",
      "description": "Grants permission to import the IdP certificate used for verifying external IdP responses",
      "accessLevel": "Write",
      "resourceTypes": [],
      "conditionKeys": [],
      "dependentActions": []
    },
    {
      "name": "IsMemberInGroup",
      "documentationUrl": "https://docs.aws.amazon.com/singlesignon/latest/IdentityStoreAPIReference/API_IsMemberInGroups.html",
      "description": "Grants permission to check if a member is a part of the group in the directory that AWS IAM Identity Center provides by default",
      "accessLevel": "Read",
      "resourceTypes": [],
      "conditionKeys": [],
      "dependentActions": []
    },
    {
      "name": "IsMemberInGroups",
      "documentationUrl": "https://docs.aws.amazon.com/singlesignon/latest/IdentityStoreAPIReference/API_IsMemberInGroups.html",
      "description": "Grants permission to check if a member is a part of multiple groups in the directory that AWS IAM Identity Center provides by default",
      "accessLevel": "Read",
      "resourceTypes": [],
      "conditionKeys": [],
      "dependentActions": []
    },
    {
      "name": "ListBearerTokens",
      "documentationUrl": "https://docs.aws.amazon.com/singlesignon/latest/userguide/iam-auth-access-using-id-policies.html#policyexample",
      "description": "Grants permission to list bearer tokens for a given provisioning tenant",
      "accessLevel": "Read",
      "resourceTypes": [],
      "conditionKeys": [],
      "dependentActions": []
    },
    {
      "name": "ListExternalIdPCertificates",
      "documentationUrl": "https://docs.aws.amazon.com/singlesignon/latest/userguide/iam-auth-access-using-id-policies.html#policyexample",
      "description": "Grants permission to list the external IdP certificates of a given directory and IdP",
      "accessLevel": "Read",
      "resourceTypes": [],
      "conditionKeys": [],
      "dependentActions": []
    },
    {
      "name": "ListExternalIdPConfigurationsForDirectory",
      "documentationUrl": "https://docs.aws.amazon.com/singlesignon/latest/userguide/iam-auth-access-using-id-policies.html#policyexample",
      "description": "Grants permission to list all the External Identity Provider configurations created for the directory",
      "accessLevel": "Read",
      "resourceTypes": [],
      "conditionKeys": [],
      "dependentActions": []
    },
    {
      "name": "ListGroups",
      "documentationUrl": "https://docs.aws.amazon.com/singlesignon/latest/IdentityStoreAPIReference/API_ListGroups.html",
      "description": "Grants permission to list groups from the directory that AWS IAM Identity Center provides by default",
      "accessLevel": "Read",
      "resourceTypes": [],
      "conditionKeys": [],
      "dependentActions": []
    },
    {
      "name": "ListGroupsForMember",
      "documentationUrl": "https://docs.aws.amazon.com/singlesignon/latest/IdentityStoreAPIReference/API_ListGroupMembershipsForMember.html",
      "description": "Grants permission to list groups of the target member",
      "accessLevel": "Read",
      "resourceTypes": [],
      "conditionKeys": [],
      "dependentActions": []
    },
    {
      "name": "ListGroupsForUser",
      "documentationUrl": "https://docs.aws.amazon.com/singlesignon/latest/IdentityStoreAPIReference/API_ListGroupMembershipsForMember.html",
      "description": "Grants permission to list groups for a user from the directory that AWS IAM Identity Center provides by default",
      "accessLevel": "Read",
      "resourceTypes": [],
      "conditionKeys": [],
      "dependentActions": []
    },
    {
      "name": "ListMembersInGroup",
      "documentationUrl": "https://docs.aws.amazon.com/singlesignon/latest/IdentityStoreAPIReference/API_ListGroupMemberships.html",
      "description": "Grants permission to retrieve all members that are part of a group in the directory that AWS IAM Identity Center provides by default",
      "accessLevel": "Read",
      "resourceTypes": [],
      "conditionKeys": [],
      "dependentActions": []
    },
    {
      "name": "ListMfaDevicesForUser",
      "documentationUrl": "https://docs.aws.amazon.com/singlesignon/latest/userguide/iam-auth-access-using-id-policies.html#policyexample",
      "description": "Grants permission to list all active MFA devices and their MFA device metadata for a user",
      "accessLevel": "Read",
      "resourceTypes": [],
      "conditionKeys": [],
      "dependentActions": []
    },
    {
      "name": "ListProvisioningTenants",
      "documentationUrl": "https://docs.aws.amazon.com/singlesignon/latest/userguide/iam-auth-access-using-id-policies.html#policyexample",
      "description": "Grants permission to list provisioning tenants for a given directory",
      "accessLevel": "Read",
      "resourceTypes": [],
      "conditionKeys": [],
      "dependentActions": []
    },
    {
      "name": "ListUsers",
      "documentationUrl": "https://docs.aws.amazon.com/singlesignon/latest/IdentityStoreAPIReference/API_ListUsers.html",
      "description": "Grants permission to list users from the directory that AWS IAM Identity Center provides by default",
      "accessLevel": "Read",
      "resourceTypes": [],
      "conditionKeys": [],
      "dependentActions": []
    },
    {
      "name": "RemoveMemberFromGroup",
      "documentationUrl": "https://docs.aws.amazon.com/singlesignon/latest/IdentityStoreAPIReference/API_DeleteGroupMembership.html",
      "description": "Grants permission to remove a member that is part of a group in the directory that AWS IAM Identity Center provides by default",
      "accessLevel": "Write",
      "resourceTypes": [],
      "conditionKeys": [],
      "dependentActions": []
    },
    {
      "name": "SearchGroups",
      "documentationUrl": "https://docs.aws.amazon.com/singlesignon/latest/userguide/iam-auth-access-using-id-policies.html#policyexample",
      "description": "Grants permission to search for groups within the associated directory",
      "accessLevel": "Read",
      "resourceTypes": [],
      "conditionKeys": [],
      "dependentActions": []
    },
    {
      "name": "SearchUsers",
      "documentationUrl": "https://docs.aws.amazon.com/singlesignon/latest/userguide/iam-auth-access-using-id-policies.html#policyexample",
      "description": "Grants permission to search for users within the associated directory",
      "accessLevel": "Read",
      "resourceTypes": [],
      "conditionKeys": [],
      "dependentActions": []
    },
    {
      "name": "StartVirtualMfaDeviceRegistration",
      "documentationUrl": "https://docs.aws.amazon.com/singlesignon/latest/userguide/iam-auth-access-using-id-policies.html#policyexample",
      "description": "Grants permission to begin the creation process of virtual mfa device",
      "accessLevel": "Write",
      "resourceTypes": [],
      "conditionKeys": [],
      "dependentActions": []
    },
    {
      "name": "StartWebAuthnDeviceRegistration",
      "documentationUrl": "https://docs.aws.amazon.com/singlesignon/latest/userguide/iam-auth-access-using-id-policies.html#policyexample",
      "description": "Grants permission to begin the registration process of a WebAuthn device",
      "accessLevel": "Write",
      "resourceTypes": [],
      "conditionKeys": [],
      "dependentActions": []
    },
    {
      "name": "UpdateExternalIdPConfigurationForDirectory",
      "documentationUrl": "https://docs.aws.amazon.com/singlesignon/latest/userguide/iam-auth-access-using-id-policies.html#policyexample",
      "description": "Grants permission to update an External Identity Provider configuration associated with the directory",
      "accessLevel": "Write",
      "resourceTypes": [],
      "conditionKeys": [],
      "dependentActions": []
    },
    {
      "name": "UpdateGroup",
      "documentationUrl": "https://docs.aws.amazon.com/singlesignon/latest/IdentityStoreAPIReference/API_UpdateGroup.html",
      "description": "Grants permission to update information about a group in the directory that AWS IAM Identity Center provides by default",
      "accessLevel": "Write",
      "resourceTypes": [],
      "conditionKeys": [],
      "dependentActions": []
    },
    {
      "name": "UpdateGroupDisplayName",
      "documentationUrl": "https://docs.aws.amazon.com/singlesignon/latest/userguide/iam-auth-access-using-id-policies.html#policyexample",
      "description": "Grants permission to update group display name update group display name response",
      "accessLevel": "Write",
      "resourceTypes": [],
      "conditionKeys": [],
      "dependentActions": []
    },
    {
      "name": "UpdateMfaDeviceForUser",
      "documentationUrl": "https://docs.aws.amazon.com/singlesignon/latest/userguide/iam-auth-access-using-id-policies.html#policyexample",
      "description": "Grants permission to update MFA device information",
      "accessLevel": "Write",
      "resourceTypes": [],
      "conditionKeys": [],
      "dependentActions": []
    },
    {
      "name": "UpdatePassword",
      "documentationUrl": "https://docs.aws.amazon.com/singlesignon/latest/userguide/iam-auth-access-using-id-policies.html#policyexample",
      "description": "Grants permission to update a password by sending password reset link via email or generating one time password for a user in the directory that AWS IAM Identity Center provides by default",
      "accessLevel": "Write",
      "resourceTypes": [],
      "conditionKeys": [],
      "dependentActions": []
    },
    {
      "name": "UpdateUser",
      "documentationUrl": "https://docs.aws.amazon.com/singlesignon/latest/IdentityStoreAPIReference/API_UpdateUser.html",
      "description": "Grants permission to update user information in the directory that AWS IAM Identity Center provides by default",
      "accessLevel": "Write",
      "resourceTypes": [],
      "conditionKeys": [],
      "dependentActions": []
    },
    {
      "name": "UpdateUserName",
      "documentationUrl": "https://docs.aws.amazon.com/singlesignon/latest/userguide/iam-auth-access-using-id-policies.html#policyexample",
      "description": "Grants permission to update user name update user name response",
      "accessLevel": "Write",
      "resourceTypes": [],
      "conditionKeys": [],
      "dependentActions": []
    },
    {
      "name": "VerifyEmail",
      "documentationUrl": "https://docs.aws.amazon.com/singlesignon/latest/userguide/iam-auth-access-using-id-policies.html#policyexample",
      "description": "Grants permission to verify an email address of an User",
      "accessLevel": "Write",
      "resourceTypes": [],
      "conditionKeys": [],
      "dependentActions": []
    }
  ]
}