{
  "serviceName": "AWS CodeDeploy",
  "servicePrefix": "codedeploy",
  "url": "https://docs.aws.amazon.com/service-authorization/latest/reference/./list_awscodedeploy.html",
  "actions": [
    {
      "name": "AddTagsToOnPremisesInstances",
      "documentationUrl": "https://docs.aws.amazon.com/codedeploy/latest/APIReference/API_AddTagsToOnPremisesInstances.html",
      "description": "Grants permission to add tags to one or more on-premises instances",
      "accessLevel": "Tagging",
      "resourceTypes": [
        "instance*"
      ],
      "conditionKeys": [],
      "dependentActions": []
    },
    {
      "name": "BatchGetApplicationRevisions",
      "documentationUrl": "https://docs.aws.amazon.com/codedeploy/latest/APIReference/API_BatchGetApplicationRevisions.html",
      "description": "Grants permission to get information about one or more application revisions",
      "accessLevel": "Read",
      "resourceTypes": [
        "application*"
      ],
      "conditionKeys": [],
      "dependentActions": []
    },
    {
      "name": "BatchGetApplications",
      "documentationUrl": "https://docs.aws.amazon.com/codedeploy/latest/APIReference/API_BatchGetApplications.html",
      "description": "Grants permission to get information about multiple applications associated with the IAM user",
      "accessLevel": "Read",
      "resourceTypes": [
        "application*"
      ],
      "conditionKeys": [],
      "dependentActions": []
    },
    {
      "name": "BatchGetDeploymentGroups",
      "documentationUrl": "https://docs.aws.amazon.com/codedeploy/latest/APIReference/API_BatchGetDeploymentGroups.html",
      "description": "Grants permission to get information about one or more deployment groups",
      "accessLevel": "Read",
      "resourceTypes": [
        "deploymentgroup*"
      ],
      "conditionKeys": [],
      "dependentActions": []
    },
    {
      "name": "BatchGetDeploymentInstances",
      "documentationUrl": "https://docs.aws.amazon.com/codedeploy/latest/APIReference/API_BatchGetDeploymentInstances.html",
      "description": "Grants permission to get information about one or more instance that are part of a deployment group",
      "accessLevel": "Read",
      "resourceTypes": [
        "deploymentgroup*"
      ],
      "conditionKeys": [],
      "dependentActions": []
    },
    {
      "name": "BatchGetDeploymentTargets",
      "documentationUrl": "https://docs.aws.amazon.com/codedeploy/latest/APIReference/API_BatchGetDeploymentTargets.html",
      "description": "Grants permission to return an array of one or more targets associated with a deployment. This method works with all compute types and should be used instead of the deprecated BatchGetDeploymentInstances. The maximum number of targets that can be returned is 25",
      "accessLevel": "Read",
      "resourceTypes": [],
      "conditionKeys": [],
      "dependentActions": []
    },
    {
      "name": "BatchGetDeployments",
      "documentationUrl": "https://docs.aws.amazon.com/codedeploy/latest/APIReference/API_BatchGetDeployments.html",
      "description": "Grants permission to get information about multiple deployments associated with the IAM user",
      "accessLevel": "Read",
      "resourceTypes": [
        "deploymentgroup*"
      ],
      "conditionKeys": [],
      "dependentActions": []
    },
    {
      "name": "BatchGetOnPremisesInstances",
      "documentationUrl": "https://docs.aws.amazon.com/codedeploy/latest/APIReference/API_BatchGetOnPremisesInstances.html",
      "description": "Grants permission to get information about one or more on-premises instances",
      "accessLevel": "Read",
      "resourceTypes": [
        "instance*"
      ],
      "conditionKeys": [],
      "dependentActions": []
    },
    {
      "name": "ContinueDeployment",
      "documentationUrl": "https://docs.aws.amazon.com/codedeploy/latest/APIReference/API_ContinueDeployment.html",
      "description": "Grants permission to start the process of rerouting traffic from instances in the original environment to instances in thereplacement environment without waiting for a specified wait time to elapse",
      "accessLevel": "Write",
      "resourceTypes": [],
      "conditionKeys": [],
      "dependentActions": []
    },
    {
      "name": "CreateApplication",
      "documentationUrl": "https://docs.aws.amazon.com/codedeploy/latest/APIReference/API_CreateApplication.html",
      "description": "Grants permission to create an application associated with the IAM user",
      "accessLevel": "Write",
      "resourceTypes": [
        "application*"
      ],
      "conditionKeys": [
        "aws:RequestTag/${TagKey}",
        "aws:TagKeys"
      ],
      "dependentActions": []
    },
    {
      "name": "CreateCloudFormationDeployment",
      "description": "Grants permission to create CloudFormation deployment to cooperate ochestration for a CloudFormation stack update",
      "accessLevel": "Write",
      "resourceTypes": [],
      "conditionKeys": [],
      "dependentActions": []
    },
    {
      "name": "CreateDeployment",
      "documentationUrl": "https://docs.aws.amazon.com/codedeploy/latest/APIReference/API_CreateDeployment.html",
      "description": "Grants permission to create a deployment for an application associated with the IAM user",
      "accessLevel": "Write",
      "resourceTypes": [
        "deploymentgroup*"
      ],
      "conditionKeys": [],
      "dependentActions": []
    },
    {
      "name": "CreateDeploymentConfig",
      "documentationUrl": "https://docs.aws.amazon.com/codedeploy/latest/APIReference/API_CreateDeploymentConfig.html",
      "description": "Grants permission to create a custom deployment configuration associated with the IAM user",
      "accessLevel": "Write",
      "resourceTypes": [
        "deploymentconfig*"
      ],
      "conditionKeys": [],
      "dependentActions": []
    },
    {
      "name": "CreateDeploymentGroup",
      "documentationUrl": "https://docs.aws.amazon.com/codedeploy/latest/APIReference/API_CreateDeploymentGroup.html",
      "description": "Grants permission to create a deployment group for an application associated with the IAM user",
      "accessLevel": "Write",
      "resourceTypes": [
        "deploymentgroup*"
      ],
      "conditionKeys": [
        "aws:RequestTag/${TagKey}",
        "aws:TagKeys"
      ],
      "dependentActions": []
    },
    {
      "name": "DeleteApplication",
      "documentationUrl": "https://docs.aws.amazon.com/codedeploy/latest/APIReference/API_DeleteApplication.html",
      "description": "Grants permission to delete an application associated with the IAM user",
      "accessLevel": "Write",
      "resourceTypes": [
        "application*"
      ],
      "conditionKeys": [],
      "dependentActions": []
    },
    {
      "name": "DeleteDeploymentConfig",
      "documentationUrl": "https://docs.aws.amazon.com/codedeploy/latest/APIReference/API_DeleteDeploymentConfig.html",
      "description": "Grants permission to delete a custom deployment configuration associated with the IAM user",
      "accessLevel": "Write",
      "resourceTypes": [
        "deploymentconfig*"
      ],
      "conditionKeys": [],
      "dependentActions": []
    },
    {
      "name": "DeleteDeploymentGroup",
      "documentationUrl": "https://docs.aws.amazon.com/codedeploy/latest/APIReference/API_DeleteDeploymentGroup.html",
      "description": "Grants permission to delete a deployment group for an application associated with the IAM user",
      "accessLevel": "Write",
      "resourceTypes": [
        "deploymentgroup*"
      ],
      "conditionKeys": [],
      "dependentActions": []
    },
    {
      "name": "DeleteGitHubAccountToken",
      "documentationUrl": "https://docs.aws.amazon.com/codedeploy/latest/APIReference/API_DeleteGitHubAccountToken.html",
      "description": "Grants permission to delete a GitHub account connection",
      "accessLevel": "Write",
      "resourceTypes": [],
      "conditionKeys": [],
      "dependentActions": []
    },
    {
      "name": "DeleteResourcesByExternalId",
      "documentationUrl": "https://docs.aws.amazon.com/codedeploy/latest/APIReference/API_DeleteResourcesByExternalId.html",
      "description": "Grants permission to delete resources associated with the given external Id",
      "accessLevel": "Write",
      "resourceTypes": [],
      "conditionKeys": [],
      "dependentActions": []
    },
    {
      "name": "DeregisterOnPremisesInstance",
      "documentationUrl": "https://docs.aws.amazon.com/codedeploy/latest/APIReference/API_DeregisterOnPremisesInstance.html",
      "description": "Grants permission to deregister an on-premises instance",
      "accessLevel": "Write",
      "resourceTypes": [
        "instance*"
      ],
      "conditionKeys": [],
      "dependentActions": []
    },
    {
      "name": "GetApplication",
      "documentationUrl": "https://docs.aws.amazon.com/codedeploy/latest/APIReference/API_GetApplication.html",
      "description": "Grants permission to get information about a single application associated with the IAM user",
      "accessLevel": "List",
      "resourceTypes": [
        "application*"
      ],
      "conditionKeys": [],
      "dependentActions": []
    },
    {
      "name": "GetApplicationRevision",
      "documentationUrl": "https://docs.aws.amazon.com/codedeploy/latest/APIReference/API_GetApplicationRevision.html",
      "description": "Grants permission to get information about a single application revision for an application associated with the IAM user",
      "accessLevel": "List",
      "resourceTypes": [
        "application*"
      ],
      "conditionKeys": [],
      "dependentActions": []
    },
    {
      "name": "GetDeployment",
      "documentationUrl": "https://docs.aws.amazon.com/codedeploy/latest/APIReference/API_GetDeployment.html",
      "description": "Grants permission to get information about a single deployment to a deployment group for an application associated with the IAM user",
      "accessLevel": "List",
      "resourceTypes": [
        "deploymentgroup*"
      ],
      "conditionKeys": [],
      "dependentActions": []
    },
    {
      "name": "GetDeploymentConfig",
      "documentationUrl": "https://docs.aws.amazon.com/codedeploy/latest/APIReference/API_GetDeploymentConfig.html",
      "description": "Grants permission to get information about a single deployment configuration associated with the IAM user",
      "accessLevel": "List",
      "resourceTypes": [
        "deploymentconfig*"
      ],
      "conditionKeys": [],
      "dependentActions": []
    },
    {
      "name": "GetDeploymentGroup",
      "documentationUrl": "https://docs.aws.amazon.com/codedeploy/latest/APIReference/API_GetDeploymentGroup.html",
      "description": "Grants permission to get information about a single deployment group for an application associated with the IAM user",
      "accessLevel": "List",
      "resourceTypes": [
        "deploymentgroup*"
      ],
      "conditionKeys": [],
      "dependentActions": []
    },
    {
      "name": "GetDeploymentInstance",
      "documentationUrl": "https://docs.aws.amazon.com/codedeploy/latest/APIReference/API_GetDeploymentInstance.html",
      "description": "Grants permission to get information about a single instance in a deployment associated with the IAM user",
      "accessLevel": "List",
      "resourceTypes": [
        "deploymentgroup*"
      ],
      "conditionKeys": [],
      "dependentActions": []
    },
    {
      "name": "GetDeploymentTarget",
      "documentationUrl": "https://docs.aws.amazon.com/codedeploy/latest/APIReference/API_GetDeploymentTarget.html",
      "description": "Grants permission to return information about a deployment target",
      "accessLevel": "Read",
      "resourceTypes": [],
      "conditionKeys": [],
      "dependentActions": []
    },
    {
      "name": "GetOnPremisesInstance",
      "documentationUrl": "https://docs.aws.amazon.com/codedeploy/latest/APIReference/API_GetOnPremisesInstance.html",
      "description": "Grants permission to get information about a single on-premises instance",
      "accessLevel": "List",
      "resourceTypes": [
        "instance*"
      ],
      "conditionKeys": [],
      "dependentActions": []
    },
    {
      "name": "ListApplicationRevisions",
      "documentationUrl": "https://docs.aws.amazon.com/codedeploy/latest/APIReference/API_ListApplicationRevisions.html",
      "description": "Grants permission to get information about all application revisions for an application associated with the IAM user",
      "accessLevel": "List",
      "resourceTypes": [
        "application*"
      ],
      "conditionKeys": [],
      "dependentActions": []
    },
    {
      "name": "ListApplications",
      "documentationUrl": "https://docs.aws.amazon.com/codedeploy/latest/APIReference/API_ListApplications.html",
      "description": "Grants permission to get information about all applications associated with the IAM user",
      "accessLevel": "List",
      "resourceTypes": [],
      "conditionKeys": [],
      "dependentActions": []
    },
    {
      "name": "ListDeploymentConfigs",
      "documentationUrl": "https://docs.aws.amazon.com/codedeploy/latest/APIReference/API_ListDeploymentConfigs.html",
      "description": "Grants permission to get information about all deployment configurations associated with the IAM user",
      "accessLevel": "List",
      "resourceTypes": [],
      "conditionKeys": [],
      "dependentActions": []
    },
    {
      "name": "ListDeploymentGroups",
      "documentationUrl": "https://docs.aws.amazon.com/codedeploy/latest/APIReference/API_ListDeploymentGroups.html",
      "description": "Grants permission to get information about all deployment groups for an application associated with the IAM user",
      "accessLevel": "List",
      "resourceTypes": [
        "application*"
      ],
      "conditionKeys": [],
      "dependentActions": []
    },
    {
      "name": "ListDeploymentInstances",
      "documentationUrl": "https://docs.aws.amazon.com/codedeploy/latest/APIReference/API_ListDeploymentInstances.html",
      "description": "Grants permission to get information about all instances in a deployment associated with the IAM user",
      "accessLevel": "List",
      "resourceTypes": [
        "deploymentgroup*"
      ],
      "conditionKeys": [],
      "dependentActions": []
    },
    {
      "name": "ListDeploymentTargets",
      "documentationUrl": "https://docs.aws.amazon.com/codedeploy/latest/APIReference/API_ListDeploymentTargets.html",
      "description": "Grants permission to return an array of target IDs that are associated a deployment",
      "accessLevel": "List",
      "resourceTypes": [],
      "conditionKeys": [],
      "dependentActions": []
    },
    {
      "name": "ListDeployments",
      "documentationUrl": "https://docs.aws.amazon.com/codedeploy/latest/APIReference/API_ListDeployments.html",
      "description": "Grants permission to get information about all deployments to a deployment group associated with the IAM user, or to get all deployments associated with the IAM user",
      "accessLevel": "List",
      "resourceTypes": [
        "deploymentgroup*"
      ],
      "conditionKeys": [],
      "dependentActions": []
    },
    {
      "name": "ListGitHubAccountTokenNames",
      "documentationUrl": "https://docs.aws.amazon.com/codedeploy/latest/APIReference/API_ListGitHubAccountTokenNames.html",
      "description": "Grants permission to list the names of stored connections to GitHub accounts",
      "accessLevel": "List",
      "resourceTypes": [],
      "conditionKeys": [],
      "dependentActions": []
    },
    {
      "name": "ListOnPremisesInstances",
      "documentationUrl": "https://docs.aws.amazon.com/codedeploy/latest/APIReference/API_ListOnPremisesInstances.html",
      "description": "Grants permission to get a list of one or more on-premises instance names",
      "accessLevel": "List",
      "resourceTypes": [],
      "conditionKeys": [],
      "dependentActions": []
    },
    {
      "name": "ListTagsForResource",
      "documentationUrl": "https://docs.aws.amazon.com/codedeploy/latest/APIReference/API_ListTagsForResource.html",
      "description": "Grants permission to return a list of tags for the resource identified by a specified ARN. Tags are used to organize and categorize your CodeDeploy resources",
      "accessLevel": "List",
      "resourceTypes": [
        "application",
        "deploymentgroup"
      ],
      "conditionKeys": [],
      "dependentActions": []
    },
    {
      "name": "PutLifecycleEventHookExecutionStatus",
      "documentationUrl": "https://docs.aws.amazon.com/codedeploy/latest/APIReference/API_PutLifecycleEventHookExecutionStatus.html",
      "description": "Grants permission to notify a lifecycle event hook execution status for associated deployment with the IAM user",
      "accessLevel": "Write",
      "resourceTypes": [],
      "conditionKeys": [],
      "dependentActions": []
    },
    {
      "name": "RegisterApplicationRevision",
      "documentationUrl": "https://docs.aws.amazon.com/codedeploy/latest/APIReference/API_RegisterApplicationRevision.html",
      "description": "Grants permission to register information about an application revision for an application associated with the IAM user",
      "accessLevel": "Write",
      "resourceTypes": [
        "application*"
      ],
      "conditionKeys": [],
      "dependentActions": []
    },
    {
      "name": "RegisterOnPremisesInstance",
      "documentationUrl": "https://docs.aws.amazon.com/codedeploy/latest/APIReference/API_RegisterOnPremisesInstance.html",
      "description": "Grants permission to register an on-premises instance",
      "accessLevel": "Write",
      "resourceTypes": [
        "instance*"
      ],
      "conditionKeys": [],
      "dependentActions": []
    },
    {
      "name": "RemoveTagsFromOnPremisesInstances",
      "documentationUrl": "https://docs.aws.amazon.com/codedeploy/latest/APIReference/API_RemoveTagsFromOnPremisesInstances.html",
      "description": "Grants permission to remove tags from one or more on-premises instances",
      "accessLevel": "Tagging",
      "resourceTypes": [
        "instance*"
      ],
      "conditionKeys": [],
      "dependentActions": []
    },
    {
      "name": "SkipWaitTimeForInstanceTermination",
      "documentationUrl": "https://docs.aws.amazon.com/codedeploy/latest/APIReference/API_SkipWaitTimeForInstanceTermination.html",
      "description": "Grants permission to override any specified wait time and starts terminating instances immediately after the traffic routing is complete. This action applies to blue-green deployments only",
      "accessLevel": "Write",
      "resourceTypes": [],
      "conditionKeys": [],
      "dependentActions": []
    },
    {
      "name": "StopDeployment",
      "documentationUrl": "https://docs.aws.amazon.com/codedeploy/latest/APIReference/API_StopDeployment.html",
      "description": "Grants permission to stop a deployment",
      "accessLevel": "Write",
      "resourceTypes": [],
      "conditionKeys": [],
      "dependentActions": []
    },
    {
      "name": "TagResource",
      "documentationUrl": "https://docs.aws.amazon.com/codedeploy/latest/APIReference/API_TagResource.html",
      "description": "Grants permission to associate the list of tags in the input Tags parameter with the resource identified by the ResourceArn input parameter",
      "accessLevel": "Tagging",
      "resourceTypes": [
        "application",
        "deploymentgroup"
      ],
      "conditionKeys": [
        "aws:RequestTag/${TagKey}",
        "aws:TagKeys"
      ],
      "dependentActions": []
    },
    {
      "name": "UntagResource",
      "documentationUrl": "https://docs.aws.amazon.com/codedeploy/latest/APIReference/API_UntagResource.html",
      "description": "Grants permission to disassociate a resource from a list of tags. The resource is identified by the ResourceArn input parameter. The tags are identfied by the list of keys in the TagKeys input parameter",
      "accessLevel": "Tagging",
      "resourceTypes": [
        "application",
        "deploymentgroup"
      ],
      "conditionKeys": [
        "aws:TagKeys"
      ],
      "dependentActions": []
    },
    {
      "name": "UpdateApplication",
      "documentationUrl": "https://docs.aws.amazon.com/codedeploy/latest/APIReference/API_UpdateApplication.html",
      "description": "Grants permission to update an application",
      "accessLevel": "Write",
      "resourceTypes": [
        "application*"
      ],
      "conditionKeys": [],
      "dependentActions": []
    },
    {
      "name": "UpdateDeploymentGroup",
      "documentationUrl": "https://docs.aws.amazon.com/codedeploy/latest/APIReference/API_UpdateDeploymentGroup.html",
      "description": "Grants permission to change information about a single deployment group for an application associated with the IAM user",
      "accessLevel": "Write",
      "resourceTypes": [
        "deploymentgroup*"
      ],
      "conditionKeys": [],
      "dependentActions": []
    }
  ]
}